{
"meta":{"test_sets":[],"test_metrics":[],"learn_metrics":[{"best_value":"Min","name":"RMSE"}],"launch_mode":"Train","parameters":"","iteration_count":1000,"learn_sets":["learn"],"name":"experiment"},
"iterations":[
{"learn":[440.797632],"iteration":0,"passed_time":0.007051974301,"remaining_time":7.044922327},
{"learn":[437.7538337],"iteration":1,"passed_time":0.0126770857,"remaining_time":6.325865764},
{"learn":[435.0818788],"iteration":2,"passed_time":0.01770689322,"remaining_time":5.884590846},
{"learn":[432.2985327],"iteration":3,"passed_time":0.02080325877,"remaining_time":5.180011434},
{"learn":[429.4670063],"iteration":4,"passed_time":0.02355616893,"remaining_time":4.687677617},
{"learn":[426.8085676],"iteration":5,"passed_time":0.02780583337,"remaining_time":4.606499728},
{"learn":[423.9708783],"iteration":6,"passed_time":0.0313032371,"remaining_time":4.440587777},
{"learn":[421.6461609],"iteration":7,"passed_time":0.03493778434,"remaining_time":4.332285258},
{"learn":[418.4393418],"iteration":8,"passed_time":0.03952037784,"remaining_time":4.351632715},
{"learn":[415.6611882],"iteration":9,"passed_time":0.04344138524,"remaining_time":4.300697139},
{"learn":[413.2064206],"iteration":10,"passed_time":0.0473102297,"remaining_time":4.253619743},
{"learn":[410.5587989],"iteration":11,"passed_time":0.05157825922,"remaining_time":4.246610009},
{"learn":[408.4582279],"iteration":12,"passed_time":0.05495160566,"remaining_time":4.172094984},
{"learn":[406.4195835],"iteration":13,"passed_time":0.05816785318,"remaining_time":4.096678802},
{"learn":[403.9903265],"iteration":14,"passed_time":0.06165192229,"remaining_time":4.048476231},
{"learn":[401.0157591],"iteration":15,"passed_time":0.06501289076,"remaining_time":3.998292782},
{"learn":[398.2734859],"iteration":16,"passed_time":0.06812110282,"remaining_time":3.939002592},
{"learn":[395.1804768],"iteration":17,"passed_time":0.0824463126,"remaining_time":4.497904388},
{"learn":[392.1373651],"iteration":18,"passed_time":0.08435592795,"remaining_time":4.355429754},
{"learn":[389.5115673],"iteration":19,"passed_time":0.08599331755,"remaining_time":4.21367256},
{"learn":[387.3430215],"iteration":20,"passed_time":0.08930243087,"remaining_time":4.163194277},
{"learn":[384.5005686],"iteration":21,"passed_time":0.09261293523,"remaining_time":4.117065939},
{"learn":[382.1516025],"iteration":22,"passed_time":0.09597749441,"remaining_time":4.076957045},
{"learn":[380.2307705],"iteration":23,"passed_time":0.09932530284,"remaining_time":4.039228982},
{"learn":[377.4838749],"iteration":24,"passed_time":0.1026791135,"remaining_time":4.004485426},
{"learn":[375.3810625],"iteration":25,"passed_time":0.1060909591,"remaining_time":3.974330543},
{"learn":[372.2340122],"iteration":26,"passed_time":0.1094530133,"remaining_time":3.944362296},
{"learn":[369.5659812],"iteration":27,"passed_time":0.1129427935,"remaining_time":3.920728403},
{"learn":[366.9111014],"iteration":28,"passed_time":0.1170127529,"remaining_time":3.917909761},
{"learn":[364.496662],"iteration":29,"passed_time":0.1204392566,"remaining_time":3.89420263},
{"learn":[362.1773914],"iteration":30,"passed_time":0.1244381063,"remaining_time":3.889694355},
{"learn":[360.172332],"iteration":31,"passed_time":0.1328822514,"remaining_time":4.019688104},
{"learn":[358.0415806],"iteration":32,"passed_time":0.1395547454,"remaining_time":4.089376934},
{"learn":[355.6431238],"iteration":33,"passed_time":0.1449363653,"remaining_time":4.117897907},
{"learn":[353.319805],"iteration":34,"passed_time":0.1490526607,"remaining_time":4.109594788},
{"learn":[351.2562727],"iteration":35,"passed_time":0.1521879122,"remaining_time":4.075254093},
{"learn":[348.8576284],"iteration":36,"passed_time":0.1552949063,"remaining_time":4.041864723},
{"learn":[345.905407],"iteration":37,"passed_time":0.156910487,"remaining_time":3.972312855},
{"learn":[343.3974457],"iteration":38,"passed_time":0.158551919,"remaining_time":3.906881902},
{"learn":[341.0111825],"iteration":39,"passed_time":0.1611556956,"remaining_time":3.867736694},
{"learn":[338.3694426],"iteration":40,"passed_time":0.1640985068,"remaining_time":3.838304098},
{"learn":[336.1461715],"iteration":41,"passed_time":0.1676451774,"remaining_time":3.823906665},
{"learn":[334.4411214],"iteration":42,"passed_time":0.1710390059,"remaining_time":3.806612294},
{"learn":[332.2476957],"iteration":43,"passed_time":0.1743567581,"remaining_time":3.788296835},
{"learn":[330.4963932],"iteration":44,"passed_time":0.1774510476,"remaining_time":3.765905566},
{"learn":[328.7754322],"iteration":45,"passed_time":0.1817511027,"remaining_time":3.769359826},
{"learn":[326.5678059],"iteration":46,"passed_time":0.186139501,"remaining_time":3.774275414},
{"learn":[324.9709266],"iteration":47,"passed_time":0.1896722564,"remaining_time":3.761833085},
{"learn":[322.3465222],"iteration":48,"passed_time":0.1930358287,"remaining_time":3.746470879},
{"learn":[320.6559343],"iteration":49,"passed_time":0.1969413479,"remaining_time":3.741885611},
{"learn":[318.8561604],"iteration":50,"passed_time":0.2003614065,"remaining_time":3.728293623},
{"learn":[317.2261606],"iteration":51,"passed_time":0.2026040598,"remaining_time":3.693627859},
{"learn":[315.0683529],"iteration":52,"passed_time":0.2050395301,"remaining_time":3.66363085},
{"learn":[313.5870042],"iteration":53,"passed_time":0.2067334754,"remaining_time":3.621664217},
{"learn":[311.8971786],"iteration":54,"passed_time":0.2100725165,"remaining_time":3.609427783},
{"learn":[310.1592447],"iteration":55,"passed_time":0.2161693354,"remaining_time":3.643997369},
{"learn":[307.9057522],"iteration":56,"passed_time":0.2185547222,"remaining_time":3.61573865},
{"learn":[306.1269893],"iteration":57,"passed_time":0.2226389884,"remaining_time":3.61596426},
{"learn":[304.4311364],"iteration":58,"passed_time":0.2316782011,"remaining_time":3.69507097},
{"learn":[302.6471018],"iteration":59,"passed_time":0.2393458994,"remaining_time":3.749752424},
{"learn":[300.6712636],"iteration":60,"passed_time":0.2435269539,"remaining_time":3.748718191},
{"learn":[298.8047434],"iteration":61,"passed_time":0.2468467629,"remaining_time":3.734552639},
{"learn":[297.0146672],"iteration":62,"passed_time":0.2809524416,"remaining_time":4.178610124},
{"learn":[294.9317528],"iteration":63,"passed_time":0.2825643932,"remaining_time":4.132504251},
{"learn":[293.8109542],"iteration":64,"passed_time":0.2832231958,"remaining_time":4.074056739},
{"learn":[292.2896954],"iteration":65,"passed_time":0.2848242557,"remaining_time":4.03069477},
{"learn":[290.5190039],"iteration":66,"passed_time":0.2864200481,"remaining_time":3.988506043},
{"learn":[288.6630363],"iteration":67,"passed_time":0.2880173413,"remaining_time":3.947531795},
{"learn":[287.1482305],"iteration":68,"passed_time":0.2902376394,"remaining_time":3.916104961},
{"learn":[285.481021],"iteration":69,"passed_time":0.2930393222,"remaining_time":3.893236709},
{"learn":[283.995628],"iteration":70,"passed_time":0.2946163835,"remaining_time":3.854910144},
{"learn":[282.8909715],"iteration":71,"passed_time":0.2961944217,"remaining_time":3.817616991},
{"learn":[281.4944392],"iteration":72,"passed_time":0.2977733494,"remaining_time":3.781313628},
{"learn":[279.939349],"iteration":73,"passed_time":0.2993617434,"remaining_time":3.746067221},
{"learn":[278.3033228],"iteration":74,"passed_time":0.3009575244,"remaining_time":3.711809468},
{"learn":[276.5354377],"iteration":75,"passed_time":0.3025244945,"remaining_time":3.678060959},
{"learn":[274.8814583],"iteration":76,"passed_time":0.3044510407,"remaining_time":3.649458579},
{"learn":[273.2920287],"iteration":77,"passed_time":0.307613666,"remaining_time":3.636151282},
{"learn":[271.4793801],"iteration":78,"passed_time":0.3114631045,"remaining_time":3.631107839},
{"learn":[269.9567175],"iteration":79,"passed_time":0.3171152291,"remaining_time":3.646825135},
{"learn":[268.5417043],"iteration":80,"passed_time":0.3252505275,"remaining_time":3.690188084},
{"learn":[267.2147657],"iteration":81,"passed_time":0.3299690079,"remaining_time":3.694043283},
{"learn":[265.8779329],"iteration":82,"passed_time":0.3335765242,"remaining_time":3.685417743},
{"learn":[264.2266404],"iteration":83,"passed_time":0.3367023097,"remaining_time":3.67165852},
{"learn":[262.6034238],"iteration":84,"passed_time":0.3425849994,"remaining_time":3.687826758},
{"learn":[261.0316352],"iteration":85,"passed_time":0.3458782703,"remaining_time":3.675962082},
{"learn":[259.2778692],"iteration":86,"passed_time":0.3495353668,"remaining_time":3.668112527},
{"learn":[257.8416021],"iteration":87,"passed_time":0.3511823918,"remaining_time":3.639526606},
{"learn":[256.5144594],"iteration":88,"passed_time":0.3529549728,"remaining_time":3.612831239},
{"learn":[255.4575243],"iteration":89,"passed_time":0.3572501853,"remaining_time":3.612196318},
{"learn":[254.4961195],"iteration":90,"passed_time":0.3606198521,"remaining_time":3.602235666},
{"learn":[253.0400088],"iteration":91,"passed_time":0.3656415293,"remaining_time":3.60872292},
{"learn":[251.9100272],"iteration":92,"passed_time":0.369110025,"remaining_time":3.599814975},
{"learn":[250.4742859],"iteration":93,"passed_time":0.3727986179,"remaining_time":3.593144125},
{"learn":[249.0810375],"iteration":94,"passed_time":0.377481431,"remaining_time":3.596007316},
{"learn":[247.7750217],"iteration":95,"passed_time":0.382016204,"remaining_time":3.597319254},
{"learn":[246.0741497],"iteration":96,"passed_time":0.3874417764,"remaining_time":3.606803341},
{"learn":[244.487051],"iteration":97,"passed_time":0.3981111294,"remaining_time":3.664247334},
{"learn":[242.9975295],"iteration":98,"passed_time":0.403201676,"remaining_time":3.669542526},
{"learn":[242.095817],"iteration":99,"passed_time":0.4073992657,"remaining_time":3.666593391},
{"learn":[241.3147596],"iteration":100,"passed_time":0.4116374597,"remaining_time":3.663980953},
{"learn":[240.0062718],"iteration":101,"passed_time":0.4157467723,"remaining_time":3.660201976},
{"learn":[238.2981598],"iteration":102,"passed_time":0.4195009579,"remaining_time":3.653323876},
{"learn":[237.1620716],"iteration":103,"passed_time":0.4230571701,"remaining_time":3.644800235},
{"learn":[236.017641],"iteration":104,"passed_time":0.4255008051,"remaining_time":3.626887815},
{"learn":[234.637419],"iteration":105,"passed_time":0.4278790131,"remaining_time":3.60871545},
{"learn":[232.8655259],"iteration":106,"passed_time":0.4360331593,"remaining_time":3.639043096},
{"learn":[231.2916881],"iteration":107,"passed_time":0.4394256536,"remaining_time":3.629330398},
{"learn":[230.3292536],"iteration":108,"passed_time":0.4431942929,"remaining_time":3.622808394},
{"learn":[228.7877547],"iteration":109,"passed_time":0.4466131353,"remaining_time":3.613506277},
{"learn":[227.6739103],"iteration":110,"passed_time":0.4487329179,"remaining_time":3.593905982},
{"learn":[226.7047073],"iteration":111,"passed_time":0.4538432284,"remaining_time":3.598328454},
{"learn":[225.4791363],"iteration":112,"passed_time":0.458713648,"remaining_time":3.600699166},
{"learn":[223.9888239],"iteration":113,"passed_time":0.4628787755,"remaining_time":3.59746136},
{"learn":[223.0624135],"iteration":114,"passed_time":0.4676082501,"remaining_time":3.598550447},
{"learn":[221.8344235],"iteration":115,"passed_time":0.4709517696,"remaining_time":3.588977278},
{"learn":[220.820188],"iteration":116,"passed_time":0.474943883,"remaining_time":3.584405544},
{"learn":[219.6933186],"iteration":117,"passed_time":0.4781552642,"remaining_time":3.574007992},
{"learn":[218.6153042],"iteration":118,"passed_time":0.4797924512,"remaining_time":3.552076887},
{"learn":[217.5490993],"iteration":119,"passed_time":0.4822705979,"remaining_time":3.536651051},
{"learn":[217.0878991],"iteration":120,"passed_time":0.4842905081,"remaining_time":3.518110386},
{"learn":[216.0951134],"iteration":121,"passed_time":0.4859304827,"remaining_time":3.497106261},
{"learn":[215.0403514],"iteration":122,"passed_time":0.4875469684,"remaining_time":3.476249523},
{"learn":[213.5385864],"iteration":123,"passed_time":0.4898184433,"remaining_time":3.460330293},
{"learn":[212.0760304],"iteration":124,"passed_time":0.4916296442,"remaining_time":3.44140751},
{"learn":[211.4802398],"iteration":125,"passed_time":0.4941863071,"remaining_time":3.427927241},
{"learn":[210.3047658],"iteration":126,"passed_time":0.4970147123,"remaining_time":3.416486959},
{"learn":[209.2966425],"iteration":127,"passed_time":0.5004103869,"remaining_time":3.409045761},
{"learn":[208.2530673],"iteration":128,"passed_time":0.5049650593,"remaining_time":3.409492765},
{"learn":[207.1120795],"iteration":129,"passed_time":0.5083772876,"remaining_time":3.402217232},
{"learn":[205.7546719],"iteration":130,"passed_time":0.5124639498,"remaining_time":3.399474598},
{"learn":[204.663237],"iteration":131,"passed_time":0.5158779596,"remaining_time":3.392288401},
{"learn":[203.5422761],"iteration":132,"passed_time":0.5205126234,"remaining_time":3.393116124},
{"learn":[202.6170966],"iteration":133,"passed_time":0.5222972259,"remaining_time":3.375443266},
{"learn":[201.5075635],"iteration":134,"passed_time":0.5239704998,"remaining_time":3.357292462},
{"learn":[200.4085519],"iteration":135,"passed_time":0.5269298141,"remaining_time":3.347554113},
{"learn":[199.401421],"iteration":136,"passed_time":0.5285610785,"remaining_time":3.329548984},
{"learn":[198.259375],"iteration":137,"passed_time":0.5301923061,"remaining_time":3.311780926},
{"learn":[197.3295131],"iteration":138,"passed_time":0.5339556451,"remaining_time":3.307451874},
{"learn":[196.2495348],"iteration":139,"passed_time":0.5386073468,"remaining_time":3.308587987},
{"learn":[195.2444476],"iteration":140,"passed_time":0.5417109598,"remaining_time":3.300210741},
{"learn":[194.1921338],"iteration":141,"passed_time":0.5440030091,"remaining_time":3.287004097},
{"learn":[193.2838],"iteration":142,"passed_time":0.5475784449,"remaining_time":3.281641449},
{"learn":[192.5710232],"iteration":143,"passed_time":0.5506230343,"remaining_time":3.273148037},
{"learn":[191.3647352],"iteration":144,"passed_time":0.5537957614,"remaining_time":3.265485352},
{"learn":[190.368472],"iteration":145,"passed_time":0.5570829994,"remaining_time":3.258553983},
{"learn":[189.1301249],"iteration":146,"passed_time":0.5602616166,"remaining_time":3.251041898},
{"learn":[188.1014493],"iteration":147,"passed_time":0.5634785679,"remaining_time":3.243809053},
{"learn":[187.0538471],"iteration":148,"passed_time":0.5667380291,"remaining_time":3.236872904},
{"learn":[186.5945548],"iteration":149,"passed_time":0.5700185769,"remaining_time":3.230105269},
{"learn":[185.5833174],"iteration":150,"passed_time":0.5739541767,"remaining_time":3.227066861},
{"learn":[184.8593939],"iteration":151,"passed_time":0.5771785383,"remaining_time":3.220048687},
{"learn":[183.7047046],"iteration":152,"passed_time":0.5803106036,"remaining_time":3.212569158},
{"learn":[182.6895175],"iteration":153,"passed_time":0.5832168606,"remaining_time":3.203905611},
{"learn":[181.5792563],"iteration":154,"passed_time":0.586361081,"remaining_time":3.196613635},
{"learn":[180.7603312],"iteration":155,"passed_time":0.5890474974,"remaining_time":3.186897999},
{"learn":[179.8232088],"iteration":156,"passed_time":0.5906884253,"remaining_time":3.171658233},
{"learn":[178.9638242],"iteration":157,"passed_time":0.6002171763,"remaining_time":3.198625712},
{"learn":[178.2351599],"iteration":158,"passed_time":0.6036935262,"remaining_time":3.193121104},
{"learn":[177.4414485],"iteration":159,"passed_time":0.6071342455,"remaining_time":3.187454789},
{"learn":[176.4724769],"iteration":160,"passed_time":0.6115083422,"remaining_time":3.186680119},
{"learn":[175.8088386],"iteration":161,"passed_time":0.6150161328,"remaining_time":3.181379748},
{"learn":[174.7402599],"iteration":162,"passed_time":0.6184853437,"remaining_time":3.175903268},
{"learn":[173.9271703],"iteration":163,"passed_time":0.6219882906,"remaining_time":3.170623237},
{"learn":[172.9530419],"iteration":164,"passed_time":0.6243307161,"remaining_time":3.159491806},
{"learn":[172.0724971],"iteration":165,"passed_time":0.6259630025,"remaining_time":3.144898459},
{"learn":[171.2950945],"iteration":166,"passed_time":0.6279874926,"remaining_time":3.132416655},
{"learn":[170.3801682],"iteration":167,"passed_time":0.6301237259,"remaining_time":3.120612738},
{"learn":[169.1124797],"iteration":168,"passed_time":0.6317425231,"remaining_time":3.106378915},
{"learn":[168.1988276],"iteration":169,"passed_time":0.6334032167,"remaining_time":3.092498058},
{"learn":[167.3446609],"iteration":170,"passed_time":0.6365935571,"remaining_time":3.086175783},
{"learn":[166.5045482],"iteration":171,"passed_time":0.6405184534,"remaining_time":3.083426043},
{"learn":[165.5517198],"iteration":172,"passed_time":0.6430052689,"remaining_time":3.073788193},
{"learn":[164.7520869],"iteration":173,"passed_time":0.6452320321,"remaining_time":3.062998037},
{"learn":[163.9197666],"iteration":174,"passed_time":0.6488506084,"remaining_time":3.058867154},
{"learn":[163.4893058],"iteration":175,"passed_time":0.6508089016,"remaining_time":3.046968948},
{"learn":[162.5176426],"iteration":176,"passed_time":0.6542003854,"remaining_time":3.04184699},
{"learn":[161.4618087],"iteration":177,"passed_time":0.6575412253,"remaining_time":3.036510602},
{"learn":[160.6668402],"iteration":178,"passed_time":0.6607886012,"remaining_time":3.03076783},
{"learn":[159.8006465],"iteration":179,"passed_time":0.6627369382,"remaining_time":3.019134941},
{"learn":[159.3756668],"iteration":180,"passed_time":0.6667254606,"remaining_time":3.01684062},
{"learn":[158.9141454],"iteration":181,"passed_time":0.6707181302,"remaining_time":3.014546321},
{"learn":[157.9533279],"iteration":182,"passed_time":0.672393111,"remaining_time":3.001886184},
{"learn":[157.08233],"iteration":183,"passed_time":0.6740280839,"remaining_time":2.989168024},
{"learn":[156.1049346],"iteration":184,"passed_time":0.6756677211,"remaining_time":2.976590231},
{"learn":[155.209441],"iteration":185,"passed_time":0.6772971823,"remaining_time":2.964085518},
{"learn":[154.2361575],"iteration":186,"passed_time":0.6821092208,"remaining_time":2.965533671},
{"learn":[153.3857289],"iteration":187,"passed_time":0.6854011947,"remaining_time":2.960349841},
{"learn":[152.420334],"iteration":188,"passed_time":0.6900521062,"remaining_time":2.961017239},
{"learn":[151.3799568],"iteration":189,"passed_time":0.7038458507,"remaining_time":3.000605995},
{"learn":[150.5741336],"iteration":190,"passed_time":0.705510059,"remaining_time":2.988259883},
{"learn":[149.4154897],"iteration":191,"passed_time":0.7071010041,"remaining_time":2.975716725},
{"learn":[149.0998475],"iteration":192,"passed_time":0.7086902809,"remaining_time":2.963280087},
{"learn":[148.1203497],"iteration":193,"passed_time":0.7119696458,"remaining_time":2.957976982},
{"learn":[147.3563023],"iteration":194,"passed_time":0.7152655342,"remaining_time":2.952762846},
{"learn":[146.7207008],"iteration":195,"passed_time":0.7185979316,"remaining_time":2.947718046},
{"learn":[146.2454093],"iteration":196,"passed_time":0.721933093,"remaining_time":2.942701897},
{"learn":[145.1780976],"iteration":197,"passed_time":0.7255688375,"remaining_time":2.938920241},
{"learn":[144.479129],"iteration":198,"passed_time":0.7288292232,"remaining_time":2.933629185},
{"learn":[143.8203214],"iteration":199,"passed_time":0.7377478114,"remaining_time":2.950991246},
{"learn":[143.0731622],"iteration":200,"passed_time":0.7418967783,"remaining_time":2.949131969},
{"learn":[142.6998341],"iteration":201,"passed_time":0.7450628544,"remaining_time":2.943367118},
{"learn":[141.6788743],"iteration":202,"passed_time":0.748489819,"remaining_time":2.938652147},
{"learn":[141.3121196],"iteration":203,"passed_time":0.7558655018,"remaining_time":2.949357546},
{"learn":[140.2875827],"iteration":204,"passed_time":0.7888602893,"remaining_time":3.059238683},
{"learn":[139.2995952],"iteration":205,"passed_time":0.792179141,"remaining_time":3.05335067},
{"learn":[138.4901557],"iteration":206,"passed_time":0.7953585753,"remaining_time":3.046953383},
{"learn":[137.7099795],"iteration":207,"passed_time":0.7976443688,"remaining_time":3.037184327},
{"learn":[137.0063751],"iteration":208,"passed_time":0.8046802821,"remaining_time":3.045464608},
{"learn":[136.6027824],"iteration":209,"passed_time":0.8079482357,"remaining_time":3.039424315},
{"learn":[135.9256732],"iteration":210,"passed_time":0.8112393796,"remaining_time":3.033497016},
{"learn":[135.334193],"iteration":211,"passed_time":0.8196543516,"remaining_time":3.04663976},
{"learn":[134.497556],"iteration":212,"passed_time":0.82302062,"remaining_time":3.040925953},
{"learn":[133.5936225],"iteration":213,"passed_time":0.8263689377,"remaining_time":3.035168154},
{"learn":[132.6113367],"iteration":214,"passed_time":0.8333457447,"remaining_time":3.042680975},
{"learn":[131.8769448],"iteration":215,"passed_time":0.837831021,"remaining_time":3.041016299},
{"learn":[131.5656503],"iteration":216,"passed_time":0.8411814429,"remaining_time":3.035230736},
{"learn":[131.0746273],"iteration":217,"passed_time":0.8494112675,"remaining_time":3.046970694},
{"learn":[130.7321267],"iteration":218,"passed_time":0.8545022224,"remaining_time":3.047334409},
{"learn":[129.901859],"iteration":219,"passed_time":0.8563532935,"remaining_time":3.036161677},
{"learn":[128.8772385],"iteration":220,"passed_time":0.8580792975,"remaining_time":3.024632456},
{"learn":[128.4426277],"iteration":221,"passed_time":0.8637222186,"remaining_time":3.026918406},
{"learn":[127.6552615],"iteration":222,"passed_time":0.8681497877,"remaining_time":3.024898588},
{"learn":[126.9944031],"iteration":223,"passed_time":0.8698679537,"remaining_time":3.013471125},
{"learn":[126.7113922],"iteration":224,"passed_time":0.8732554777,"remaining_time":3.007879979},
{"learn":[126.4242207],"iteration":225,"passed_time":0.8750002827,"remaining_time":2.996682384},
{"learn":[126.1154844],"iteration":226,"passed_time":0.8830509147,"remaining_time":3.00704122},
{"learn":[125.2001619],"iteration":227,"passed_time":0.8864249221,"remaining_time":3.001403684},
{"learn":[124.4894167],"iteration":228,"passed_time":0.8899368969,"remaining_time":2.996250426},
{"learn":[124.0930774],"iteration":229,"passed_time":0.8954793274,"remaining_time":2.997909053},
{"learn":[123.2687971],"iteration":230,"passed_time":0.898129994,"remaining_time":2.989878638},
{"learn":[122.5442515],"iteration":231,"passed_time":0.8998329132,"remaining_time":2.97875723},
{"learn":[122.2818457],"iteration":232,"passed_time":0.9036307702,"remaining_time":2.974612879},
{"learn":[121.7647068],"iteration":233,"passed_time":0.9090382712,"remaining_time":2.975740666},
{"learn":[121.4810346],"iteration":234,"passed_time":0.9140267249,"remaining_time":2.9754487},
{"learn":[121.158553],"iteration":235,"passed_time":0.9167398807,"remaining_time":2.967751139},
{"learn":[120.4096325],"iteration":236,"passed_time":0.9191665018,"remaining_time":2.959173168},
{"learn":[119.4479572],"iteration":237,"passed_time":0.9217776727,"remaining_time":2.951237759},
{"learn":[118.7436169],"iteration":238,"passed_time":0.9252940191,"remaining_time":2.946229073},
{"learn":[118.4564568],"iteration":239,"passed_time":0.9286617619,"remaining_time":2.940762246},
{"learn":[118.2225277],"iteration":240,"passed_time":0.9309548612,"remaining_time":2.93192838},
{"learn":[117.9069523],"iteration":241,"passed_time":0.9336915041,"remaining_time":2.924537852},
{"learn":[117.4985165],"iteration":242,"passed_time":0.9371710148,"remaining_time":2.919499828},
{"learn":[116.754627],"iteration":243,"passed_time":0.9406610611,"remaining_time":2.914507222},
{"learn":[115.9764148],"iteration":244,"passed_time":0.9443809986,"remaining_time":2.910235322},
{"learn":[115.1520199],"iteration":245,"passed_time":0.9481820118,"remaining_time":2.90621641},
{"learn":[114.4148177],"iteration":246,"passed_time":0.9519384956,"remaining_time":2.902063511},
{"learn":[113.5616654],"iteration":247,"passed_time":0.9555587535,"remaining_time":2.897500736},
{"learn":[112.860164],"iteration":248,"passed_time":0.9603633157,"remaining_time":2.89651747},
{"learn":[112.0509698],"iteration":249,"passed_time":0.9637882482,"remaining_time":2.891364745},
{"learn":[111.1952414],"iteration":250,"passed_time":0.9661962245,"remaining_time":2.883191124},
{"learn":[110.9578559],"iteration":251,"passed_time":0.9685101343,"remaining_time":2.874784049},
{"learn":[110.281001],"iteration":252,"passed_time":0.9709931129,"remaining_time":2.866924329},
{"learn":[110.0547608],"iteration":253,"passed_time":0.9735103909,"remaining_time":2.859207683},
{"learn":[109.8205479],"iteration":254,"passed_time":0.9755820758,"remaining_time":2.850229986},
{"learn":[109.3140325],"iteration":255,"passed_time":0.9789774969,"remaining_time":2.84515335},
{"learn":[108.6660238],"iteration":256,"passed_time":0.9821257183,"remaining_time":2.839375131},
{"learn":[107.7394515],"iteration":257,"passed_time":0.9838539427,"remaining_time":2.829533432},
{"learn":[107.1233878],"iteration":258,"passed_time":0.9875253822,"remaining_time":2.825313931},
{"learn":[106.3627355],"iteration":259,"passed_time":0.9911369085,"remaining_time":2.820928124},
{"learn":[106.1159075],"iteration":260,"passed_time":0.994727013,"remaining_time":2.816487596},
{"learn":[105.6374227],"iteration":261,"passed_time":0.9982384888,"remaining_time":2.811832079},
{"learn":[104.9363157],"iteration":262,"passed_time":1.003134945,"remaining_time":2.811066367},
{"learn":[104.4401949],"iteration":263,"passed_time":1.007111121,"remaining_time":2.807703731},
{"learn":[104.2402499],"iteration":264,"passed_time":1.010338132,"remaining_time":2.802258592},
{"learn":[104.0152795],"iteration":265,"passed_time":1.012936745,"remaining_time":2.795096131},
{"learn":[103.2228851],"iteration":266,"passed_time":1.017006679,"remaining_time":2.7920071},
{"learn":[102.9504228],"iteration":267,"passed_time":1.019492624,"remaining_time":2.784584332},
{"learn":[102.3857297],"iteration":268,"passed_time":1.022144631,"remaining_time":2.777649535},
{"learn":[101.5826731],"iteration":269,"passed_time":1.024301414,"remaining_time":2.769407526},
{"learn":[100.8637931],"iteration":270,"passed_time":1.027778542,"remaining_time":2.764762203},
{"learn":[100.2590159],"iteration":271,"passed_time":1.032321529,"remaining_time":2.76297821},
{"learn":[99.38368402],"iteration":272,"passed_time":1.035963189,"remaining_time":2.758773767},
{"learn":[99.130299],"iteration":273,"passed_time":1.040413966,"remaining_time":2.756717298},
{"learn":[98.84391848],"iteration":274,"passed_time":1.043868665,"remaining_time":2.75201739},
{"learn":[98.07785203],"iteration":275,"passed_time":1.049246961,"remaining_time":2.752372464},
{"learn":[97.3700686],"iteration":276,"passed_time":1.052689318,"remaining_time":2.74763313},
{"learn":[96.6238963],"iteration":277,"passed_time":1.055488767,"remaining_time":2.741233417},
{"learn":[96.28279852],"iteration":278,"passed_time":1.057188143,"remaining_time":2.732016671},
{"learn":[95.54232794],"iteration":279,"passed_time":1.059513727,"remaining_time":2.72446387},
{"learn":[94.91209079],"iteration":280,"passed_time":1.063007627,"remaining_time":2.719937666},
{"learn":[94.27810498],"iteration":281,"passed_time":1.066548829,"remaining_time":2.715539218},
{"learn":[93.55145449],"iteration":282,"passed_time":1.070670613,"remaining_time":2.712617773},
{"learn":[92.96341552],"iteration":283,"passed_time":1.07408136,"remaining_time":2.70789526},
{"learn":[92.29981682],"iteration":284,"passed_time":1.07920881,"remaining_time":2.707488769},
{"learn":[91.58641029],"iteration":285,"passed_time":1.082740066,"remaining_time":2.703064361},
{"learn":[91.4040336],"iteration":286,"passed_time":1.087730588,"remaining_time":2.702271461},
{"learn":[90.8254231],"iteration":287,"passed_time":1.091316038,"remaining_time":2.697975761},
{"learn":[90.25462769],"iteration":288,"passed_time":1.0974172,"remaining_time":2.69987415},
{"learn":[89.83359061],"iteration":289,"passed_time":1.100030494,"remaining_time":2.693178106},
{"learn":[89.1491999],"iteration":290,"passed_time":1.102143147,"remaining_time":2.685290347},
{"learn":[88.49956251],"iteration":291,"passed_time":1.10585935,"remaining_time":2.681330206},
{"learn":[87.98082055],"iteration":292,"passed_time":1.110683101,"remaining_time":2.680044207},
{"learn":[87.3577954],"iteration":293,"passed_time":1.11513618,"remaining_time":2.677844024},
{"learn":[86.66714568],"iteration":294,"passed_time":1.118597777,"remaining_time":2.673259094},
{"learn":[86.01417506],"iteration":295,"passed_time":1.121961469,"remaining_time":2.668448898},
{"learn":[85.38916013],"iteration":296,"passed_time":1.12620776,"remaining_time":2.66573756},
{"learn":[85.17137044],"iteration":297,"passed_time":1.130785789,"remaining_time":2.663797395},
{"learn":[84.49863549],"iteration":298,"passed_time":1.134879081,"remaining_time":2.660703129},
{"learn":[84.2937695],"iteration":299,"passed_time":1.140763877,"remaining_time":2.66178238},
{"learn":[83.6956617],"iteration":300,"passed_time":1.144359733,"remaining_time":2.657499844},
{"learn":[83.49382605],"iteration":301,"passed_time":1.147221937,"remaining_time":2.651526199},
{"learn":[83.28005577],"iteration":302,"passed_time":1.150626407,"remaining_time":2.646820481},
{"learn":[82.71312081],"iteration":303,"passed_time":1.154064806,"remaining_time":2.642201003},
{"learn":[82.15152286],"iteration":304,"passed_time":1.15791323,"remaining_time":2.638523589},
{"learn":[81.54063129],"iteration":305,"passed_time":1.161298437,"remaining_time":2.633794495},
{"learn":[81.06725999],"iteration":306,"passed_time":1.164863399,"remaining_time":2.629479919},
{"learn":[80.77136664],"iteration":307,"passed_time":1.192070104,"remaining_time":2.678287376},
{"learn":[80.14454117],"iteration":308,"passed_time":1.194076011,"remaining_time":2.67024765},
{"learn":[79.94944537],"iteration":309,"passed_time":1.201838765,"remaining_time":2.675060476},
{"learn":[79.44020359],"iteration":310,"passed_time":1.20375455,"remaining_time":2.666838859},
{"learn":[78.87640181],"iteration":311,"passed_time":1.20773338,"remaining_time":2.663206941},
{"learn":[78.32712673],"iteration":312,"passed_time":1.211041823,"remaining_time":2.658101382},
{"learn":[77.75628905],"iteration":313,"passed_time":1.214356199,"remaining_time":2.653020232},
{"learn":[77.17136658],"iteration":314,"passed_time":1.217775488,"remaining_time":2.648178442},
{"learn":[76.9147069],"iteration":315,"passed_time":1.221119378,"remaining_time":2.643182451},
{"learn":[76.47296662],"iteration":316,"passed_time":1.223681282,"remaining_time":2.636512036},
{"learn":[75.94471279],"iteration":317,"passed_time":1.225339525,"remaining_time":2.627929421},
{"learn":[75.40965493],"iteration":318,"passed_time":1.226991021,"remaining_time":2.619375817},
{"learn":[75.20330596],"iteration":319,"passed_time":1.228649705,"remaining_time":2.610880624},
{"learn":[74.6880356],"iteration":320,"passed_time":1.230350126,"remaining_time":2.602516309},
{"learn":[74.512615],"iteration":321,"passed_time":1.232026181,"remaining_time":2.594142083},
{"learn":[73.99154082],"iteration":322,"passed_time":1.235136596,"remaining_time":2.588815714},
{"learn":[73.48284205],"iteration":323,"passed_time":1.238414732,"remaining_time":2.58385296},
{"learn":[72.97935479],"iteration":324,"passed_time":1.252226793,"remaining_time":2.600778724},
{"learn":[72.42309434],"iteration":325,"passed_time":1.262838949,"remaining_time":2.610900157},
{"learn":[71.92605368],"iteration":326,"passed_time":1.26740202,"remaining_time":2.608445136},
{"learn":[71.73214954],"iteration":327,"passed_time":1.270756675,"remaining_time":2.603501481},
{"learn":[71.17529425],"iteration":328,"passed_time":1.275420633,"remaining_time":2.601237827},
{"learn":[70.69646363],"iteration":329,"passed_time":1.282256268,"remaining_time":2.603368787},
{"learn":[70.45630638],"iteration":330,"passed_time":1.285596682,"remaining_time":2.59838121},
{"learn":[69.89980409],"iteration":331,"passed_time":1.288113359,"remaining_time":2.591746156},
{"learn":[69.39360461],"iteration":332,"passed_time":1.291365577,"remaining_time":2.586609128},
{"learn":[68.88188746],"iteration":333,"passed_time":1.293718328,"remaining_time":2.57968984},
{"learn":[68.32264752],"iteration":334,"passed_time":1.296822768,"remaining_time":2.574289973},
{"learn":[68.16842235],"iteration":335,"passed_time":1.298981966,"remaining_time":2.56703579},
{"learn":[67.6347985],"iteration":336,"passed_time":1.300643453,"remaining_time":2.558832669},
{"learn":[67.42748669],"iteration":337,"passed_time":1.303575462,"remaining_time":2.553156675},
{"learn":[66.96550756],"iteration":338,"passed_time":1.305824545,"remaining_time":2.546165263},
{"learn":[66.43389636],"iteration":339,"passed_time":1.307921532,"remaining_time":2.538906504},
{"learn":[65.97128948],"iteration":340,"passed_time":1.311996731,"remaining_time":2.535501014},
{"learn":[65.46065262],"iteration":341,"passed_time":1.313678667,"remaining_time":2.527487027},
{"learn":[64.94546647],"iteration":342,"passed_time":1.315321592,"remaining_time":2.519435237},
{"learn":[64.59230001],"iteration":343,"passed_time":1.317953459,"remaining_time":2.513306596},
{"learn":[64.08708252],"iteration":344,"passed_time":1.319580728,"remaining_time":2.505290947},
{"learn":[63.69655969],"iteration":345,"passed_time":1.321792452,"remaining_time":2.498416946},
{"learn":[63.23361312],"iteration":346,"passed_time":1.32525492,"remaining_time":2.493923523},
{"learn":[62.84566633],"iteration":347,"passed_time":1.330517544,"remaining_time":2.492808731},
{"learn":[62.35818098],"iteration":348,"passed_time":1.334202257,"remaining_time":2.488726845},
{"learn":[61.93359148],"iteration":349,"passed_time":1.33756184,"remaining_time":2.484043418},
{"learn":[61.72505327],"iteration":350,"passed_time":1.341667987,"remaining_time":2.48074793},
{"learn":[61.51875618],"iteration":351,"passed_time":1.345362159,"remaining_time":2.476689428},
{"learn":[61.03892859],"iteration":352,"passed_time":1.347603102,"remaining_time":2.469969426},
{"learn":[60.70944573],"iteration":353,"passed_time":1.349246602,"remaining_time":2.462184477},
{"learn":[60.49605509],"iteration":354,"passed_time":1.350859604,"remaining_time":2.454378716},
{"learn":[60.05391593],"iteration":355,"passed_time":1.352468421,"remaining_time":2.446600178},
{"learn":[59.73334895],"iteration":356,"passed_time":1.355390222,"remaining_time":2.441221045},
{"learn":[59.52479172],"iteration":357,"passed_time":1.35971042,"remaining_time":2.43836338},
{"learn":[59.32896259],"iteration":358,"passed_time":1.362726737,"remaining_time":2.433169467},
{"learn":[58.97075138],"iteration":359,"passed_time":1.36582673,"remaining_time":2.42813641},
{"learn":[58.58906883],"iteration":360,"passed_time":1.370003944,"remaining_time":2.425020831},
{"learn":[58.39765379],"iteration":361,"passed_time":1.374302529,"remaining_time":2.422113297},
{"learn":[57.9439056],"iteration":362,"passed_time":1.378034441,"remaining_time":2.418203689},
{"learn":[57.63380005],"iteration":363,"passed_time":1.382906013,"remaining_time":2.41628633},
{"learn":[57.50206072],"iteration":364,"passed_time":1.387242521,"remaining_time":2.41342192},
{"learn":[57.17358582],"iteration":365,"passed_time":1.393105541,"remaining_time":2.413193751},
{"learn":[56.97795882],"iteration":366,"passed_time":1.399859337,"remaining_time":2.414471282},
{"learn":[56.85296923],"iteration":367,"passed_time":1.401983801,"remaining_time":2.407754789},
{"learn":[56.44243243],"iteration":368,"passed_time":1.404189234,"remaining_time":2.401201645},
{"learn":[56.14212973],"iteration":369,"passed_time":1.407653477,"remaining_time":2.39681538},
{"learn":[56.01903495],"iteration":370,"passed_time":1.411878718,"remaining_time":2.393724295},
{"learn":[55.72191043],"iteration":371,"passed_time":1.415308938,"remaining_time":2.389284981},
{"learn":[55.40289924],"iteration":372,"passed_time":1.41872591,"remaining_time":2.384828809},
{"learn":[55.26064294],"iteration":373,"passed_time":1.422154439,"remaining_time":2.380397537},
{"learn":[54.8488205],"iteration":374,"passed_time":1.424702291,"remaining_time":2.374503818},
{"learn":[54.47202041],"iteration":375,"passed_time":1.428351005,"remaining_time":2.37045486},
{"learn":[54.35024193],"iteration":376,"passed_time":1.43164705,"remaining_time":2.365825232},
{"learn":[53.93409602],"iteration":377,"passed_time":1.436484141,"remaining_time":2.363738455},
{"learn":[53.81344745],"iteration":378,"passed_time":1.440076926,"remaining_time":2.359598341},
{"learn":[53.49642541],"iteration":379,"passed_time":1.443673017,"remaining_time":2.355466502},
{"learn":[53.1078613],"iteration":380,"passed_time":1.447149129,"remaining_time":2.351142549},
{"learn":[52.82867007],"iteration":381,"passed_time":1.450938197,"remaining_time":2.347329334},
{"learn":[52.71099274],"iteration":382,"passed_time":1.453633756,"remaining_time":2.34175464},
{"learn":[52.59447494],"iteration":383,"passed_time":1.455287576,"remaining_time":2.334523819},
{"learn":[52.25800341],"iteration":384,"passed_time":1.456939012,"remaining_time":2.327318162},
{"learn":[52.14328144],"iteration":385,"passed_time":1.458570723,"remaining_time":2.320109907},
{"learn":[52.02968789],"iteration":386,"passed_time":1.462174403,"remaining_time":2.316054029},
{"learn":[51.69137765],"iteration":387,"passed_time":1.468068587,"remaining_time":2.315613338},
{"learn":[51.57960319],"iteration":388,"passed_time":1.471804734,"remaining_time":2.311754993},
{"learn":[51.26893367],"iteration":389,"passed_time":1.47515091,"remaining_time":2.30728732},
{"learn":[50.85020872],"iteration":390,"passed_time":1.478858881,"remaining_time":2.303388896},
{"learn":[50.4376465],"iteration":391,"passed_time":1.482744417,"remaining_time":2.299766851},
{"learn":[50.08085646],"iteration":392,"passed_time":1.486376065,"remaining_time":2.295751327},
{"learn":[49.97277501],"iteration":393,"passed_time":1.488047736,"remaining_time":2.288723167},
{"learn":[49.59935041],"iteration":394,"passed_time":1.489716631,"remaining_time":2.281717879},
{"learn":[49.30222358],"iteration":395,"passed_time":1.492939448,"remaining_time":2.277109664},
{"learn":[48.95887737],"iteration":396,"passed_time":1.494848138,"remaining_time":2.270512411},
{"learn":[48.85357788],"iteration":397,"passed_time":1.496980119,"remaining_time":2.264276461},
{"learn":[48.56185848],"iteration":398,"passed_time":1.499577046,"remaining_time":2.258761415},
{"learn":[48.19755224],"iteration":399,"passed_time":1.502930909,"remaining_time":2.254396363},
{"learn":[47.85804348],"iteration":400,"passed_time":1.507347498,"remaining_time":2.251623818},
{"learn":[47.50050858],"iteration":401,"passed_time":1.511400327,"remaining_time":2.248301979},
{"learn":[47.26430356],"iteration":402,"passed_time":1.515339181,"remaining_time":2.24480767},
{"learn":[47.1638112],"iteration":403,"passed_time":1.517761424,"remaining_time":2.239073784},
{"learn":[46.85777435],"iteration":404,"passed_time":1.520213407,"remaining_time":2.233399943},
{"learn":[46.4802767],"iteration":405,"passed_time":1.522382871,"remaining_time":2.227328635},
{"learn":[46.16783116],"iteration":406,"passed_time":1.525285339,"remaining_time":2.222344486},
{"learn":[45.79742197],"iteration":407,"passed_time":1.527256077,"remaining_time":2.216018621},
{"learn":[45.47396742],"iteration":408,"passed_time":1.530727883,"remaining_time":2.211883078},
{"learn":[45.37794445],"iteration":409,"passed_time":1.534093852,"remaining_time":2.20759847},
{"learn":[45.2829638],"iteration":410,"passed_time":1.537401559,"remaining_time":2.203234837},
{"learn":[45.01282779],"iteration":411,"passed_time":1.550854785,"remaining_time":2.213355859},
{"learn":[44.7209987],"iteration":412,"passed_time":1.55423562,"remaining_time":2.209046752},
{"learn":[44.37111345],"iteration":413,"passed_time":1.557654594,"remaining_time":2.204796115},
{"learn":[44.0483699],"iteration":414,"passed_time":1.560668361,"remaining_time":2.199978292},
{"learn":[43.66279891],"iteration":415,"passed_time":1.564095549,"remaining_time":2.195749521},
{"learn":[43.41282727],"iteration":416,"passed_time":1.567357038,"remaining_time":2.191292934},
{"learn":[43.0380083],"iteration":417,"passed_time":1.574404676,"remaining_time":2.192113688},
{"learn":[42.66958552],"iteration":418,"passed_time":1.577495321,"remaining_time":2.18740998},
{"learn":[42.30572342],"iteration":419,"passed_time":1.579471544,"remaining_time":2.181174989},
{"learn":[42.11245998],"iteration":420,"passed_time":1.581675947,"remaining_time":2.175274046},
{"learn":[41.92151798],"iteration":421,"passed_time":1.586991283,"remaining_time":2.173651568},
{"learn":[41.5667525],"iteration":422,"passed_time":1.59082374,"remaining_time":2.169988885},
{"learn":[41.21920952],"iteration":423,"passed_time":1.594404908,"remaining_time":2.165984026},
{"learn":[41.02935619],"iteration":424,"passed_time":1.59897304,"remaining_time":2.163316466},
{"learn":[40.78403995],"iteration":425,"passed_time":1.613605628,"remaining_time":2.17420101},
{"learn":[40.54202785],"iteration":426,"passed_time":1.627110376,"remaining_time":2.183452566},
{"learn":[40.35686347],"iteration":427,"passed_time":1.631652845,"remaining_time":2.180620158},
{"learn":[40.17394568],"iteration":428,"passed_time":1.635154866,"remaining_time":2.176394939},
{"learn":[39.83955911],"iteration":429,"passed_time":1.646389863,"remaining_time":2.182423772},
{"learn":[39.66015861],"iteration":430,"passed_time":1.651449279,"remaining_time":2.180219582},
{"learn":[39.33283413],"iteration":431,"passed_time":1.662252847,"remaining_time":2.18555467},
{"learn":[39.15689015],"iteration":432,"passed_time":1.676536391,"remaining_time":2.195372133},
{"learn":[38.98308329],"iteration":433,"passed_time":1.680542486,"remaining_time":2.191675224},
{"learn":[38.66395497],"iteration":434,"passed_time":1.689527066,"remaining_time":2.194443201},
{"learn":[38.49350795],"iteration":435,"passed_time":1.694284773,"remaining_time":2.191689477},
{"learn":[38.18117085],"iteration":436,"passed_time":1.70078267,"remaining_time":2.19116852},
{"learn":[38.10133799],"iteration":437,"passed_time":1.709632805,"remaining_time":2.193638439},
{"learn":[38.02227132],"iteration":438,"passed_time":1.715348808,"remaining_time":2.192051666},
{"learn":[37.85678439],"iteration":439,"passed_time":1.724178629,"remaining_time":2.194409164},
{"learn":[37.59931811],"iteration":440,"passed_time":1.731069853,"remaining_time":2.194258612},
{"learn":[37.29365621],"iteration":441,"passed_time":1.739606499,"remaining_time":2.196154811},
{"learn":[37.21710977],"iteration":442,"passed_time":1.744033803,"remaining_time":2.192837085},
{"learn":[36.96566427],"iteration":443,"passed_time":1.754929145,"remaining_time":2.197613975},
{"learn":[36.89275409],"iteration":444,"passed_time":1.761863345,"remaining_time":2.197380127},
{"learn":[36.59574226],"iteration":445,"passed_time":1.771635705,"remaining_time":2.20064166},
{"learn":[36.35021394],"iteration":446,"passed_time":1.80796295,"remaining_time":2.236696894},
{"learn":[36.27890859],"iteration":447,"passed_time":1.811296594,"remaining_time":2.23177616},
{"learn":[36.12233703],"iteration":448,"passed_time":1.818957308,"remaining_time":2.232172554},
{"learn":[35.88527701],"iteration":449,"passed_time":1.822619376,"remaining_time":2.227645905},
{"learn":[35.8132151],"iteration":450,"passed_time":1.826255047,"remaining_time":2.223090955},
{"learn":[35.5820529],"iteration":451,"passed_time":1.83321481,"remaining_time":2.222570168},
{"learn":[35.34409542],"iteration":452,"passed_time":1.837704258,"remaining_time":2.219038034},
{"learn":[35.05625154],"iteration":453,"passed_time":1.842277261,"remaining_time":2.215602168},
{"learn":[34.98630754],"iteration":454,"passed_time":1.853362581,"remaining_time":2.219961773},
{"learn":[34.70025238],"iteration":455,"passed_time":1.856833688,"remaining_time":2.215170014},
{"learn":[34.47537456],"iteration":456,"passed_time":1.863403245,"remaining_time":2.214065562},
{"learn":[34.2462454],"iteration":457,"passed_time":1.867778383,"remaining_time":2.210340357},
{"learn":[33.97467971],"iteration":458,"passed_time":1.870194027,"remaining_time":2.204302764},
{"learn":[33.75037641],"iteration":459,"passed_time":1.873234773,"remaining_time":2.199014734},
{"learn":[33.68335343],"iteration":460,"passed_time":1.880831118,"remaining_time":2.199062847},
{"learn":[33.3868856],"iteration":461,"passed_time":1.884828924,"remaining_time":2.194887361},
{"learn":[33.12467483],"iteration":462,"passed_time":1.888309834,"remaining_time":2.190113133},
{"learn":[33.0593463],"iteration":463,"passed_time":1.8917021,"remaining_time":2.185242081},
{"learn":[32.84784044],"iteration":464,"passed_time":1.895655155,"remaining_time":2.181022597},
{"learn":[32.56417904],"iteration":465,"passed_time":1.898447983,"remaining_time":2.175474727},
{"learn":[32.50044388],"iteration":466,"passed_time":1.900172218,"remaining_time":2.168719041},
{"learn":[32.22248458],"iteration":467,"passed_time":1.901872848,"remaining_time":2.161958024},
{"learn":[32.15991855],"iteration":468,"passed_time":1.903963637,"remaining_time":2.155660323},
{"learn":[31.96253167],"iteration":469,"passed_time":1.90645761,"remaining_time":2.149835177},
{"learn":[31.76752238],"iteration":470,"passed_time":1.909392755,"remaining_time":2.144519676},
{"learn":[31.64488635],"iteration":471,"passed_time":1.912513708,"remaining_time":2.139422114},
{"learn":[31.46365744],"iteration":472,"passed_time":1.915808738,"remaining_time":2.134526861},
{"learn":[31.40344597],"iteration":473,"passed_time":1.919053029,"remaining_time":2.129582054},
{"learn":[31.22195346],"iteration":474,"passed_time":1.92229887,"remaining_time":2.12464612},
{"learn":[30.99234551],"iteration":475,"passed_time":1.924702128,"remaining_time":2.118789737},
{"learn":[30.81816661],"iteration":476,"passed_time":1.927827473,"remaining_time":2.113739557},
{"learn":[30.60463318],"iteration":477,"passed_time":1.930246006,"remaining_time":2.107925554},
{"learn":[30.54802688],"iteration":478,"passed_time":1.93389641,"remaining_time":2.103465615},
{"learn":[30.37521767],"iteration":479,"passed_time":1.937353656,"remaining_time":2.098799794},
{"learn":[30.31770425],"iteration":480,"passed_time":1.947425042,"remaining_time":2.101275669},
{"learn":[30.15013789],"iteration":481,"passed_time":1.952415523,"remaining_time":2.098239089},
{"learn":[29.98516554],"iteration":482,"passed_time":1.95573968,"remaining_time":2.093410796},
{"learn":[29.93039211],"iteration":483,"passed_time":1.959299475,"remaining_time":2.088839936},
{"learn":[29.7565179],"iteration":484,"passed_time":1.965181056,"remaining_time":2.086738647},
{"learn":[29.55438532],"iteration":485,"passed_time":1.968522782,"remaining_time":2.081935617},
{"learn":[29.50054469],"iteration":486,"passed_time":1.972359602,"remaining_time":2.077660115},
{"learn":[29.33852683],"iteration":487,"passed_time":1.974377263,"remaining_time":2.071477785},
{"learn":[29.28551855],"iteration":488,"passed_time":1.976087959,"remaining_time":2.064991712},
{"learn":[29.12893506],"iteration":489,"passed_time":1.977747591,"remaining_time":2.058471983},
{"learn":[29.07667312],"iteration":490,"passed_time":1.98151392,"remaining_time":2.054155978},
{"learn":[28.8702149],"iteration":491,"passed_time":1.984924795,"remaining_time":2.049475195},
{"learn":[28.70598189],"iteration":492,"passed_time":1.987125883,"remaining_time":2.043555421},
{"learn":[28.56742789],"iteration":493,"passed_time":1.988820865,"remaining_time":2.037132303},
{"learn":[28.51649552],"iteration":494,"passed_time":1.990513597,"remaining_time":2.030725993},
{"learn":[28.32394606],"iteration":495,"passed_time":1.992190509,"remaining_time":2.024322614},
{"learn":[28.27198974],"iteration":496,"passed_time":2.000078055,"remaining_time":2.024223866},
{"learn":[28.13665539],"iteration":497,"passed_time":2.002322802,"remaining_time":2.018405716},
{"learn":[28.08261134],"iteration":498,"passed_time":2.006001577,"remaining_time":2.014041664},
{"learn":[27.89008294],"iteration":499,"passed_time":2.00975243,"remaining_time":2.00975243},
{"learn":[27.74385288],"iteration":500,"passed_time":2.012434352,"remaining_time":2.004400682},
{"learn":[27.55753039],"iteration":501,"passed_time":2.016687914,"remaining_time":2.000618688},
{"learn":[27.36619361],"iteration":502,"passed_time":2.020010548,"remaining_time":1.995914995},
{"learn":[27.31820565],"iteration":503,"passed_time":2.023276492,"remaining_time":1.991160992},
{"learn":[27.13035089],"iteration":504,"passed_time":2.02612619,"remaining_time":1.98600488},
{"learn":[26.98711894],"iteration":505,"passed_time":2.029609501,"remaining_time":1.981476469},
{"learn":[26.9402194],"iteration":506,"passed_time":2.031915384,"remaining_time":1.975807267},
{"learn":[26.75678424],"iteration":507,"passed_time":2.03529115,"remaining_time":1.971187492},
{"learn":[26.63598877],"iteration":508,"passed_time":2.039071327,"remaining_time":1.966962714},
{"learn":[26.59013657],"iteration":509,"passed_time":2.04281071,"remaining_time":1.962700486},
{"learn":[26.41097374],"iteration":510,"passed_time":2.046295955,"remaining_time":1.958197107},
{"learn":[26.23466211],"iteration":511,"passed_time":2.049336345,"remaining_time":1.953273703},
{"learn":[26.1883325],"iteration":512,"passed_time":2.053942172,"remaining_time":1.949843738},
{"learn":[26.01763443],"iteration":513,"passed_time":2.058898945,"remaining_time":1.946741026},
{"learn":[25.8496972],"iteration":514,"passed_time":2.063366573,"remaining_time":1.943170462},
{"learn":[25.68447682],"iteration":515,"passed_time":2.066866999,"remaining_time":1.938689201},
{"learn":[25.55279232],"iteration":516,"passed_time":2.070234146,"remaining_time":1.934087219},
{"learn":[25.50953402],"iteration":517,"passed_time":2.074063452,"remaining_time":1.929920046},
{"learn":[25.34022917],"iteration":518,"passed_time":2.077470206,"remaining_time":1.925362561},
{"learn":[25.17541998],"iteration":519,"passed_time":2.081268443,"remaining_time":1.92117087},
{"learn":[24.9952044],"iteration":520,"passed_time":2.084764326,"remaining_time":1.916702711},
{"learn":[24.95303726],"iteration":521,"passed_time":2.088276275,"remaining_time":1.912252987},
{"learn":[24.90973353],"iteration":522,"passed_time":2.093000292,"remaining_time":1.908912312},
{"learn":[24.86686266],"iteration":523,"passed_time":2.097905885,"remaining_time":1.9057313},
{"learn":[24.73792581],"iteration":524,"passed_time":2.103123021,"remaining_time":1.90282559},
{"learn":[24.60795439],"iteration":525,"passed_time":2.108290701,"remaining_time":1.899866525},
{"learn":[24.48111983],"iteration":526,"passed_time":2.113607807,"remaining_time":1.897033193},
{"learn":[24.32119064],"iteration":527,"passed_time":2.118489249,"remaining_time":1.893800995},
{"learn":[24.28084545],"iteration":528,"passed_time":2.121945643,"remaining_time":1.889293757},
{"learn":[24.24090035],"iteration":529,"passed_time":2.127415468,"remaining_time":1.886575981},
{"learn":[24.20135184],"iteration":530,"passed_time":2.130737667,"remaining_time":1.881950972},
{"learn":[24.04562336],"iteration":531,"passed_time":2.134293174,"remaining_time":1.877536101},
{"learn":[23.87663599],"iteration":532,"passed_time":2.137750079,"remaining_time":1.873038061},
{"learn":[23.83793502],"iteration":533,"passed_time":2.141573054,"remaining_time":1.868863377},
{"learn":[23.7979738],"iteration":534,"passed_time":2.14910508,"remaining_time":1.867913761},
{"learn":[23.75841701],"iteration":535,"passed_time":2.153029072,"remaining_time":1.863816211},
{"learn":[23.60557656],"iteration":536,"passed_time":2.1606203,"remaining_time":1.86288119},
{"learn":[23.56661179],"iteration":537,"passed_time":2.163963892,"remaining_time":1.858273826},
{"learn":[23.52804334],"iteration":538,"passed_time":2.167589942,"remaining_time":1.853912734},
{"learn":[23.40757627],"iteration":539,"passed_time":2.196789737,"remaining_time":1.871339405},
{"learn":[23.28501903],"iteration":540,"passed_time":2.198684739,"remaining_time":1.865427533},
{"learn":[23.1368496],"iteration":541,"passed_time":2.200861878,"remaining_time":1.859768893},
{"learn":[22.98977002],"iteration":542,"passed_time":2.204426456,"remaining_time":1.855290774},
{"learn":[22.95370045],"iteration":543,"passed_time":2.208110722,"remaining_time":1.850916341},
{"learn":[22.91799322],"iteration":544,"passed_time":2.21161676,"remaining_time":1.846395644},
{"learn":[22.81645892],"iteration":545,"passed_time":2.215009178,"remaining_time":1.841784188},
{"learn":[22.71598017],"iteration":546,"passed_time":2.22302657,"remaining_time":1.841007379},
{"learn":[22.68086419],"iteration":547,"passed_time":2.226558049,"remaining_time":1.836504085},
{"learn":[22.58154393],"iteration":548,"passed_time":2.228990087,"remaining_time":1.831101146},
{"learn":[22.54689387],"iteration":549,"passed_time":2.232551233,"remaining_time":1.826632827},
{"learn":[22.44871712],"iteration":550,"passed_time":2.238473181,"remaining_time":1.824091576},
{"learn":[22.41300789],"iteration":551,"passed_time":2.24492935,"remaining_time":1.821971646},
{"learn":[22.31597379],"iteration":552,"passed_time":2.248685597,"remaining_time":1.817653638},
{"learn":[22.2244108],"iteration":553,"passed_time":2.253347274,"remaining_time":1.814066578},
{"learn":[22.19068115],"iteration":554,"passed_time":2.257079883,"remaining_time":1.809730717},
{"learn":[22.09555357],"iteration":555,"passed_time":2.260050111,"remaining_time":1.804788218},
{"learn":[22.06226726],"iteration":556,"passed_time":2.261844693,"remaining_time":1.798917772},
{"learn":[21.92295051],"iteration":557,"passed_time":2.264360258,"remaining_time":1.793633036},
{"learn":[21.88861383],"iteration":558,"passed_time":2.267235575,"remaining_time":1.788642019},
{"learn":[21.79521622],"iteration":559,"passed_time":2.271250677,"remaining_time":1.784554103},
{"learn":[21.65466079],"iteration":560,"passed_time":2.274702111,"remaining_time":1.78002536},
{"learn":[21.51557615],"iteration":561,"passed_time":2.276946262,"remaining_time":1.774559542},
{"learn":[21.3779486],"iteration":562,"passed_time":2.279197507,"remaining_time":1.769110676},
{"learn":[21.24210515],"iteration":563,"passed_time":2.282190813,"remaining_time":1.764246799},
{"learn":[21.10735047],"iteration":564,"passed_time":2.284242991,"remaining_time":1.758664958},
{"learn":[20.97436338],"iteration":565,"passed_time":2.288041329,"remaining_time":1.754434518},
{"learn":[20.84242817],"iteration":566,"passed_time":2.290732985,"remaining_time":1.749360463},
{"learn":[20.71188337],"iteration":567,"passed_time":2.295623541,"remaining_time":1.7459672},
{"learn":[20.58271603],"iteration":568,"passed_time":2.300403878,"remaining_time":1.742485187},
{"learn":[20.47540158],"iteration":569,"passed_time":2.311403613,"remaining_time":1.743690445},
{"learn":[20.34814337],"iteration":570,"passed_time":2.318585515,"remaining_time":1.741984564},
{"learn":[20.24299192],"iteration":571,"passed_time":2.320286341,"remaining_time":1.736158311},
{"learn":[20.13943542],"iteration":572,"passed_time":2.322033326,"remaining_time":1.730380856},
{"learn":[19.99506501],"iteration":573,"passed_time":2.323813753,"remaining_time":1.724642263},
{"learn":[19.8936614],"iteration":574,"passed_time":2.325526795,"remaining_time":1.718867631},
{"learn":[19.75225929],"iteration":575,"passed_time":2.331295037,"remaining_time":1.71609218},
{"learn":[19.65680264],"iteration":576,"passed_time":2.335215346,"remaining_time":1.711951631},
{"learn":[19.56273682],"iteration":577,"passed_time":2.338774284,"remaining_time":1.707548007},
{"learn":[19.42034928],"iteration":578,"passed_time":2.342314711,"remaining_time":1.70313384},
{"learn":[19.32358631],"iteration":579,"passed_time":2.348057444,"remaining_time":1.70031746},
{"learn":[19.18417145],"iteration":580,"passed_time":2.351673614,"remaining_time":1.695957391},
{"learn":[19.09349586],"iteration":581,"passed_time":2.355165024,"remaining_time":1.691510275},
{"learn":[19.00414356],"iteration":582,"passed_time":2.357251982,"remaining_time":1.686061881},
{"learn":[18.91128702],"iteration":583,"passed_time":2.362947836,"remaining_time":1.683195719},
{"learn":[18.77133357],"iteration":584,"passed_time":2.366053129,"remaining_time":1.678482135},
{"learn":[18.6848606],"iteration":585,"passed_time":2.368955183,"remaining_time":1.673630454},
{"learn":[18.5948741],"iteration":586,"passed_time":2.374075084,"remaining_time":1.670345843},
{"learn":[18.52399842],"iteration":587,"passed_time":2.378984312,"remaining_time":1.666907375},
{"learn":[18.44024366],"iteration":588,"passed_time":2.381846258,"remaining_time":1.662035334},
{"learn":[18.37089908],"iteration":589,"passed_time":2.385345162,"remaining_time":1.65761274},
{"learn":[18.28560145],"iteration":590,"passed_time":2.38888242,"remaining_time":1.653219813},
{"learn":[18.18640026],"iteration":591,"passed_time":2.395596576,"remaining_time":1.651019262},
{"learn":[18.10043559],"iteration":592,"passed_time":2.399231197,"remaining_time":1.646689877},
{"learn":[18.01736654],"iteration":593,"passed_time":2.400929444,"remaining_time":1.641039317},
{"learn":[17.88769053],"iteration":594,"passed_time":2.402654547,"remaining_time":1.635420322},
{"learn":[17.80700061],"iteration":595,"passed_time":2.404327578,"remaining_time":1.629779097},
{"learn":[17.7274103],"iteration":596,"passed_time":2.408329065,"remaining_time":1.62572297},
{"learn":[17.64747422],"iteration":597,"passed_time":2.411622876,"remaining_time":1.621191298},
{"learn":[17.56973703],"iteration":598,"passed_time":2.415221804,"remaining_time":1.616868019},
{"learn":[17.4872757],"iteration":599,"passed_time":2.419244156,"remaining_time":1.612829437},
{"learn":[17.41088363],"iteration":600,"passed_time":2.426710638,"remaining_time":1.611077445},
{"learn":[17.33553723],"iteration":601,"passed_time":2.430480307,"remaining_time":1.606862396},
{"learn":[17.25930517],"iteration":602,"passed_time":2.434171462,"remaining_time":1.602597132},
{"learn":[17.17983824],"iteration":603,"passed_time":2.436909873,"remaining_time":1.597709122},
{"learn":[17.10696466],"iteration":604,"passed_time":2.441170294,"remaining_time":1.593821928},
{"learn":[17.02738114],"iteration":605,"passed_time":2.443926502,"remaining_time":1.588955514},
{"learn":[16.95190031],"iteration":606,"passed_time":2.446360036,"remaining_time":1.58388714},
{"learn":[16.83545785],"iteration":607,"passed_time":2.449593235,"remaining_time":1.579343007},
{"learn":[16.765065],"iteration":608,"passed_time":2.452187684,"remaining_time":1.574393078},
{"learn":[16.69365634],"iteration":609,"passed_time":2.455762361,"remaining_time":1.570077575},
{"learn":[16.57943165],"iteration":610,"passed_time":2.457601284,"remaining_time":1.56465941},
{"learn":[16.49943694],"iteration":611,"passed_time":2.460888319,"remaining_time":1.560171025},
{"learn":[16.41731812],"iteration":612,"passed_time":2.462838375,"remaining_time":1.554842498},
{"learn":[16.29866762],"iteration":613,"passed_time":2.465538459,"remaining_time":1.54999649},
{"learn":[16.18166551],"iteration":614,"passed_time":2.467227127,"remaining_time":1.544524299},
{"learn":[16.06735299],"iteration":615,"passed_time":2.469186637,"remaining_time":1.539233228},
{"learn":[15.95744791],"iteration":616,"passed_time":2.472174249,"remaining_time":1.534591146},
{"learn":[15.84866942],"iteration":617,"passed_time":2.474135735,"remaining_time":1.529320147},
{"learn":[15.74296562],"iteration":618,"passed_time":2.47754191,"remaining_time":1.524949059},
{"learn":[15.6358677],"iteration":619,"passed_time":2.479922007,"remaining_time":1.519952198},
{"learn":[15.52986924],"iteration":620,"passed_time":2.481588131,"remaining_time":1.514528022},
{"learn":[15.46296281],"iteration":621,"passed_time":2.484134683,"remaining_time":1.509650981},
{"learn":[15.35844866],"iteration":622,"passed_time":2.486446019,"remaining_time":1.504639084},
{"learn":[15.26540836],"iteration":623,"passed_time":2.489756234,"remaining_time":1.500237731},
{"learn":[15.1617615],"iteration":624,"passed_time":2.492994094,"remaining_time":1.495796456},
{"learn":[15.09723636],"iteration":625,"passed_time":2.496238226,"remaining_time":1.491362774},
{"learn":[14.99501654],"iteration":626,"passed_time":2.498578249,"remaining_time":1.486395035},
{"learn":[14.92406332],"iteration":627,"passed_time":2.500309094,"remaining_time":1.481074814},
{"learn":[14.82333318],"iteration":628,"passed_time":2.502118887,"remaining_time":1.475812571},
{"learn":[14.71377881],"iteration":629,"passed_time":2.503795962,"remaining_time":1.470483343},
{"learn":[14.61209852],"iteration":630,"passed_time":2.505473384,"remaining_time":1.465165893},
{"learn":[14.51363072],"iteration":631,"passed_time":2.509536347,"remaining_time":1.461249012},
{"learn":[14.4147835],"iteration":632,"passed_time":2.51362656,"remaining_time":1.457347468},
{"learn":[14.3173304],"iteration":633,"passed_time":2.517595655,"remaining_time":1.45337541},
{"learn":[14.22115382],"iteration":634,"passed_time":2.521404823,"remaining_time":1.449311434},
{"learn":[14.16144214],"iteration":635,"passed_time":2.524909305,"remaining_time":1.445073879},
{"learn":[14.06608437],"iteration":636,"passed_time":2.528158415,"remaining_time":1.4406931},
{"learn":[14.00005168],"iteration":637,"passed_time":2.531704881,"remaining_time":1.436484588},
{"learn":[13.9100024],"iteration":638,"passed_time":2.535800997,"remaining_time":1.43258867},
{"learn":[13.81640737],"iteration":639,"passed_time":2.538826307,"remaining_time":1.428089798},
{"learn":[13.72809621],"iteration":640,"passed_time":2.54050311,"remaining_time":1.422840275},
{"learn":[13.67194009],"iteration":641,"passed_time":2.542184861,"remaining_time":1.417604642},
{"learn":[13.5805304],"iteration":642,"passed_time":2.543856602,"remaining_time":1.412374506},
{"learn":[13.48975162],"iteration":643,"passed_time":2.545542807,"remaining_time":1.407163415},
{"learn":[13.42719766],"iteration":644,"passed_time":2.547213992,"remaining_time":1.401954988},
{"learn":[13.33768423],"iteration":645,"passed_time":2.548874977,"remaining_time":1.396751923},
{"learn":[13.24079691],"iteration":646,"passed_time":2.551635171,"remaining_time":1.392159529},
{"learn":[13.16167326],"iteration":647,"passed_time":2.553265721,"remaining_time":1.386959157},
{"learn":[13.07402577],"iteration":648,"passed_time":2.55645446,"remaining_time":1.382612504},
{"learn":[13.01392067],"iteration":649,"passed_time":2.558200654,"remaining_time":1.37749266},
{"learn":[12.96112024],"iteration":650,"passed_time":2.560277449,"remaining_time":1.372560414},
{"learn":[12.88376372],"iteration":651,"passed_time":2.564484837,"remaining_time":1.368774115},
{"learn":[12.80707869],"iteration":652,"passed_time":2.566241306,"remaining_time":1.363684124},
{"learn":[12.73105952],"iteration":653,"passed_time":2.568850654,"remaining_time":1.359055545},
{"learn":[12.68294385],"iteration":654,"passed_time":2.571047892,"remaining_time":1.354216065},
{"learn":[12.60776497],"iteration":655,"passed_time":2.573107869,"remaining_time":1.349312663},
{"learn":[12.52420334],"iteration":656,"passed_time":2.575191325,"remaining_time":1.344430174},
{"learn":[12.47100566],"iteration":657,"passed_time":2.578319805,"remaining_time":1.340099351},
{"learn":[12.39725452],"iteration":658,"passed_time":2.581863698,"remaining_time":1.335987134},
{"learn":[12.32414487],"iteration":659,"passed_time":2.583969861,"remaining_time":1.331135989},
{"learn":[12.29728096],"iteration":660,"passed_time":2.585546162,"remaining_time":1.326021406},
{"learn":[12.22488161],"iteration":661,"passed_time":2.58887994,"remaining_time":1.321814834},
{"learn":[12.17543939],"iteration":662,"passed_time":2.5912792,"remaining_time":1.317135883},
{"learn":[12.10387201],"iteration":663,"passed_time":2.594536048,"remaining_time":1.312897759},
{"learn":[12.02403265],"iteration":664,"passed_time":2.596998293,"remaining_time":1.308262298},
{"learn":[11.92964814],"iteration":665,"passed_time":2.600311093,"remaining_time":1.304059918},
{"learn":[11.88456025],"iteration":666,"passed_time":2.603465113,"remaining_time":1.299780933},
{"learn":[11.81502812],"iteration":667,"passed_time":2.606168778,"remaining_time":1.295281489},
{"learn":[11.78922015],"iteration":668,"passed_time":2.607780693,"remaining_time":1.290247249},
{"learn":[11.71154988],"iteration":669,"passed_time":2.609473766,"remaining_time":1.285263198},
{"learn":[11.66720128],"iteration":670,"passed_time":2.612857044,"remaining_time":1.281117686},
{"learn":[11.59901717],"iteration":671,"passed_time":2.615940519,"remaining_time":1.276828111},
{"learn":[11.57387836],"iteration":672,"passed_time":2.619091901,"remaining_time":1.272575114},
{"learn":[11.50635719],"iteration":673,"passed_time":2.622262091,"remaining_time":1.268334483},
{"learn":[11.431085],"iteration":674,"passed_time":2.624466063,"remaining_time":1.263631808},
{"learn":[11.38813115],"iteration":675,"passed_time":2.627475274,"remaining_time":1.259322468},
{"learn":[11.29942205],"iteration":676,"passed_time":2.629139128,"remaining_time":1.254375093},
{"learn":[11.25410664],"iteration":677,"passed_time":2.630785128,"remaining_time":1.249428925},
{"learn":[11.17695266],"iteration":678,"passed_time":2.632383887,"remaining_time":1.244470144},
{"learn":[11.10055531],"iteration":679,"passed_time":2.634005038,"remaining_time":1.239531782},
{"learn":[11.03597057],"iteration":680,"passed_time":2.635712356,"remaining_time":1.234643527},
{"learn":[10.95411048],"iteration":681,"passed_time":2.639112316,"remaining_time":1.230553837},
{"learn":[10.89044895],"iteration":682,"passed_time":2.642259768,"remaining_time":1.22634897},
{"learn":[10.82734237],"iteration":683,"passed_time":2.644116735,"remaining_time":1.221551006},
{"learn":[10.76704296],"iteration":684,"passed_time":2.645721317,"remaining_time":1.216645569},
{"learn":[10.70485241],"iteration":685,"passed_time":2.647306596,"remaining_time":1.21174092},
{"learn":[10.63600583],"iteration":686,"passed_time":2.648916201,"remaining_time":1.206857018},
{"learn":[10.61664487],"iteration":687,"passed_time":2.650670567,"remaining_time":1.20204828},
{"learn":[10.57694738],"iteration":688,"passed_time":2.656152398,"remaining_time":1.198930908},
{"learn":[10.51593481],"iteration":689,"passed_time":2.659377987,"remaining_time":1.194793009},
{"learn":[10.45545525],"iteration":690,"passed_time":2.663304121,"remaining_time":1.190971018},
{"learn":[10.38851013],"iteration":691,"passed_time":2.667316465,"remaining_time":1.187187097},
{"learn":[10.3696387],"iteration":692,"passed_time":2.671475023,"remaining_time":1.18346729},
{"learn":[10.29446113],"iteration":693,"passed_time":2.674826012,"remaining_time":1.179390144},
{"learn":[10.22039142],"iteration":694,"passed_time":2.678645512,"remaining_time":1.175520693},
{"learn":[10.14741542],"iteration":695,"passed_time":2.682639258,"remaining_time":1.171727492},
{"learn":[10.07551914],"iteration":696,"passed_time":2.688028874,"remaining_time":1.168540529},
{"learn":[10.00468873],"iteration":697,"passed_time":2.693161176,"remaining_time":1.165235924},
{"learn":[9.929650797],"iteration":698,"passed_time":2.697117076,"remaining_time":1.161419514},
{"learn":[9.878724144],"iteration":699,"passed_time":2.701621659,"remaining_time":1.157837854},
{"learn":[9.822063978],"iteration":700,"passed_time":2.703349776,"remaining_time":1.153069305},
{"learn":[9.804223984],"iteration":701,"passed_time":2.704926622,"remaining_time":1.148245204},
{"learn":[9.735949629],"iteration":702,"passed_time":2.706837529,"remaining_time":1.143571474},
{"learn":[9.663312457],"iteration":703,"passed_time":2.709087322,"remaining_time":1.139048078},
{"learn":[9.58603543],"iteration":704,"passed_time":2.710836816,"remaining_time":1.134321788},
{"learn":[9.568662317],"iteration":705,"passed_time":2.717888093,"remaining_time":1.131811755},
{"learn":[9.551491039],"iteration":706,"passed_time":2.721928999,"remaining_time":1.128041297},
{"learn":[9.485057439],"iteration":707,"passed_time":2.725537732,"remaining_time":1.124091833},
{"learn":[9.419612266],"iteration":708,"passed_time":2.730510378,"remaining_time":1.120703131},
{"learn":[9.355142755],"iteration":709,"passed_time":2.733850521,"remaining_time":1.11664317},
{"learn":[9.291636278],"iteration":710,"passed_time":2.73809066,"remaining_time":1.112951056},
{"learn":[9.217444503],"iteration":711,"passed_time":2.742131109,"remaining_time":1.109176628},
{"learn":[9.179599339],"iteration":712,"passed_time":2.747239331,"remaining_time":1.10583126},
{"learn":[9.142294926],"iteration":713,"passed_time":2.749850364,"remaining_time":1.101480678},
{"learn":[9.084400554],"iteration":714,"passed_time":2.753585297,"remaining_time":1.097582951},
{"learn":[9.068033682],"iteration":715,"passed_time":2.756694512,"remaining_time":1.093437488},
{"learn":[9.051857352],"iteration":716,"passed_time":2.760805769,"remaining_time":1.089690422},
{"learn":[8.990610517],"iteration":717,"passed_time":2.763835512,"remaining_time":1.085517569},
{"learn":[8.930278797],"iteration":718,"passed_time":2.766745649,"remaining_time":1.081301151},
{"learn":[8.870850299],"iteration":719,"passed_time":2.770059118,"remaining_time":1.077245212},
{"learn":[8.804658134],"iteration":720,"passed_time":2.772924371,"remaining_time":1.073017891},
{"learn":[8.754436737],"iteration":721,"passed_time":2.776916923,"remaining_time":1.0692284},
{"learn":[8.724842242],"iteration":722,"passed_time":2.780222199,"remaining_time":1.065175033},
{"learn":[8.658878211],"iteration":723,"passed_time":2.784219357,"remaining_time":1.06138749},
{"learn":[8.590183247],"iteration":724,"passed_time":2.78794978,"remaining_time":1.057498193},
{"learn":[8.57485909],"iteration":725,"passed_time":2.792419272,"remaining_time":1.053888265},
{"learn":[8.524287916],"iteration":726,"passed_time":2.795682244,"remaining_time":1.049822906},
{"learn":[8.474887024],"iteration":727,"passed_time":2.798106858,"remaining_time":1.045446518},
{"learn":[8.399157067],"iteration":728,"passed_time":2.801427561,"remaining_time":1.041408599},
{"learn":[8.350708814],"iteration":729,"passed_time":2.805472241,"remaining_time":1.037640418},
{"learn":[8.317369153],"iteration":730,"passed_time":2.809572264,"remaining_time":1.033891846},
{"learn":[8.302589302],"iteration":731,"passed_time":2.813520688,"remaining_time":1.030086809},
{"learn":[8.257028559],"iteration":732,"passed_time":2.817326466,"remaining_time":1.026229422},
{"learn":[8.198572815],"iteration":733,"passed_time":2.821521866,"remaining_time":1.022513374},
{"learn":[8.140899713],"iteration":734,"passed_time":2.825872882,"remaining_time":1.018852127},
{"learn":[8.113003306],"iteration":735,"passed_time":2.830366249,"remaining_time":1.015240068},
{"learn":[8.058851283],"iteration":736,"passed_time":2.833755054,"remaining_time":1.011231451},
{"learn":[8.026791696],"iteration":737,"passed_time":2.83917655,"remaining_time":1.007946146},
{"learn":[7.970562513],"iteration":738,"passed_time":2.843475668,"remaining_time":1.004258659},
{"learn":[7.915087434],"iteration":739,"passed_time":2.84697904,"remaining_time":1.000289933},
{"learn":[7.862509209],"iteration":740,"passed_time":2.84880627,"remaining_time":0.9957366045},
{"learn":[7.835700511],"iteration":741,"passed_time":2.851978039,"remaining_time":0.9916581321},
{"learn":[7.804563975],"iteration":742,"passed_time":2.856291229,"remaining_time":0.9879769124},
{"learn":[7.750481995],"iteration":743,"passed_time":2.860296616,"remaining_time":0.984188083},
{"learn":[7.700689315],"iteration":744,"passed_time":2.863126312,"remaining_time":0.9799962544},
{"learn":[7.632864971],"iteration":745,"passed_time":2.867094184,"remaining_time":0.9761956069},
{"learn":[7.589616323],"iteration":746,"passed_time":2.870519146,"remaining_time":0.9722106345},
{"learn":[7.527684464],"iteration":747,"passed_time":2.873045028,"remaining_time":0.9679242608},
{"learn":[7.466699968],"iteration":748,"passed_time":2.876337259,"remaining_time":0.9638994019},
{"learn":[7.415149788],"iteration":749,"passed_time":2.879833378,"remaining_time":0.9599444593},
{"learn":[7.355403678],"iteration":750,"passed_time":2.883010743,"remaining_time":0.9558850534},
{"learn":[7.31587356],"iteration":751,"passed_time":2.886223646,"remaining_time":0.9518397132},
{"learn":[7.287151678],"iteration":752,"passed_time":2.890473622,"remaining_time":0.9481367658},
{"learn":[7.236959973],"iteration":753,"passed_time":2.893937502,"remaining_time":0.9441758958},
{"learn":[7.187441671],"iteration":754,"passed_time":2.897642054,"remaining_time":0.9402944412},
{"learn":[7.138587762],"iteration":755,"passed_time":2.908988438,"remaining_time":0.9388798664},
{"learn":[7.114128139],"iteration":756,"passed_time":2.913788882,"remaining_time":0.9353377785},
{"learn":[7.068462931],"iteration":757,"passed_time":2.91772417,"remaining_time":0.9315161597},
{"learn":[7.044579049],"iteration":758,"passed_time":2.921077676,"remaining_time":0.9275095125},
{"learn":[6.987886163],"iteration":759,"passed_time":2.924437419,"remaining_time":0.9235065534},
{"learn":[6.932063123],"iteration":760,"passed_time":2.926916927,"remaining_time":0.9192288378},
{"learn":[6.877097059],"iteration":761,"passed_time":2.930108854,"remaining_time":0.9151783558},
{"learn":[6.837160367],"iteration":762,"passed_time":2.933980951,"remaining_time":0.9113413962},
{"learn":[6.798332086],"iteration":763,"passed_time":2.939036266,"remaining_time":0.9078698414},
{"learn":[6.759622683],"iteration":764,"passed_time":2.943760572,"remaining_time":0.9042924634},
{"learn":[6.721301525],"iteration":765,"passed_time":2.949605776,"remaining_time":0.9010545059},
{"learn":[6.683328869],"iteration":766,"passed_time":2.954379389,"remaining_time":0.8974842213},
{"learn":[6.645993015],"iteration":767,"passed_time":2.957982311,"remaining_time":0.8935571566},
{"learn":[6.608794141],"iteration":768,"passed_time":2.961212383,"remaining_time":0.8895189342},
{"learn":[6.57144973],"iteration":769,"passed_time":2.964789158,"remaining_time":0.8855863719},
{"learn":[6.534445111],"iteration":770,"passed_time":2.967723285,"remaining_time":0.881463855},
{"learn":[6.518059573],"iteration":771,"passed_time":2.970595439,"remaining_time":0.8773261142},
{"learn":[6.481630726],"iteration":772,"passed_time":2.972650439,"remaining_time":0.8729516814},
{"learn":[6.45594729],"iteration":773,"passed_time":2.974791494,"remaining_time":0.8686083692},
{"learn":[6.419672742],"iteration":774,"passed_time":2.979056398,"remaining_time":0.8648873414},
{"learn":[6.383941816],"iteration":775,"passed_time":2.982290558,"remaining_time":0.8608673776},
{"learn":[6.348267624],"iteration":776,"passed_time":2.985728448,"remaining_time":0.8569079072},
{"learn":[6.335017144],"iteration":777,"passed_time":2.989414792,"remaining_time":0.8530206732},
{"learn":[6.299902939],"iteration":778,"passed_time":2.993242122,"remaining_time":0.8491739524},
{"learn":[6.276608586],"iteration":779,"passed_time":2.996676989,"remaining_time":0.8452165867},
{"learn":[6.241635783],"iteration":780,"passed_time":3.000122821,"remaining_time":0.8412636335},
{"learn":[6.22601737],"iteration":781,"passed_time":3.009001581,"remaining_time":0.8388265277},
{"learn":[6.191592033],"iteration":782,"passed_time":3.019983771,"remaining_time":0.836955911},
{"learn":[6.157245964],"iteration":783,"passed_time":3.02392944,"remaining_time":0.8331234172},
{"learn":[6.131898846],"iteration":784,"passed_time":3.02739806,"remaining_time":0.8291599781},
{"learn":[6.10757578],"iteration":785,"passed_time":3.03129444,"remaining_time":0.8253142624},
{"learn":[6.073928824],"iteration":786,"passed_time":3.034585154,"remaining_time":0.8213044954},
{"learn":[6.063348376],"iteration":787,"passed_time":3.037548993,"remaining_time":0.8172086122},
{"learn":[6.030027608],"iteration":788,"passed_time":3.039675552,"remaining_time":0.8128916877},
{"learn":[6.005328306],"iteration":789,"passed_time":3.045378641,"remaining_time":0.809531031},
{"learn":[5.994948376],"iteration":790,"passed_time":3.049102916,"remaining_time":0.8056416049},
{"learn":[5.984688577],"iteration":791,"passed_time":3.051183374,"remaining_time":0.801320886},
{"learn":[5.943524102],"iteration":792,"passed_time":3.055139746,"remaining_time":0.7974954949},
{"learn":[5.920070801],"iteration":793,"passed_time":3.059122707,"remaining_time":0.7936766721},
{"learn":[5.879594142],"iteration":794,"passed_time":3.063772119,"remaining_time":0.7900292885},
{"learn":[5.839662303],"iteration":795,"passed_time":3.068214487,"remaining_time":0.7863263258},
{"learn":[5.800267992],"iteration":796,"passed_time":3.072365687,"remaining_time":0.7825473455},
{"learn":[5.757829898],"iteration":797,"passed_time":3.076196599,"remaining_time":0.7786863571},
{"learn":[5.712388098],"iteration":798,"passed_time":3.079404182,"remaining_time":0.7746686366},
{"learn":[5.668383867],"iteration":799,"passed_time":3.082294746,"remaining_time":0.7705736865},
{"learn":[5.630355895],"iteration":800,"passed_time":3.084295265,"remaining_time":0.7662606214},
{"learn":[5.586345519],"iteration":801,"passed_time":3.085960591,"remaining_time":0.7618705699},
{"learn":[5.544612693],"iteration":802,"passed_time":3.089929889,"remaining_time":0.7580525381},
{"learn":[5.507574915],"iteration":803,"passed_time":3.092275949,"remaining_time":0.7538384155},
{"learn":[5.490864633],"iteration":804,"passed_time":3.093902999,"remaining_time":0.7494547637},
{"learn":[5.449301985],"iteration":805,"passed_time":3.096827627,"remaining_time":0.7453902726},
{"learn":[5.409694391],"iteration":806,"passed_time":3.100095653,"remaining_time":0.7414107325},
{"learn":[5.368932983],"iteration":807,"passed_time":3.107795237,"remaining_time":0.738485997},
{"learn":[5.333253448],"iteration":808,"passed_time":3.111310619,"remaining_time":0.7345615924},
{"learn":[5.30822991],"iteration":809,"passed_time":3.113487086,"remaining_time":0.7303241312},
{"learn":[5.2698728],"iteration":810,"passed_time":3.115742225,"remaining_time":0.726110087},
{"learn":[5.247820254],"iteration":811,"passed_time":3.124001646,"remaining_time":0.7232910214},
{"learn":[5.218365826],"iteration":812,"passed_time":3.13070483,"remaining_time":0.7201006189},
{"learn":[5.197921006],"iteration":813,"passed_time":3.134711508,"remaining_time":0.7162854307},
{"learn":[5.182150223],"iteration":814,"passed_time":3.137921665,"remaining_time":0.7122889669},
{"learn":[5.144728525],"iteration":815,"passed_time":3.139731831,"remaining_time":0.7079787462},
{"learn":[5.113703948],"iteration":816,"passed_time":3.141689625,"remaining_time":0.7037077127},
{"learn":[5.100911045],"iteration":817,"passed_time":3.145146293,"remaining_time":0.6997758257},
{"learn":[5.064188114],"iteration":818,"passed_time":3.149678121,"remaining_time":0.6960827105},
{"learn":[5.033895787],"iteration":819,"passed_time":3.153102857,"remaining_time":0.6921445295},
{"learn":[4.993166263],"iteration":820,"passed_time":3.156534327,"remaining_time":0.6882090676},
{"learn":[4.983787684],"iteration":821,"passed_time":3.159996424,"remaining_time":0.6842814642},
{"learn":[4.946721953],"iteration":822,"passed_time":3.163504096,"remaining_time":0.6803647935},
{"learn":[4.914100538],"iteration":823,"passed_time":3.166928733,"remaining_time":0.6764313799},
{"learn":[4.895116285],"iteration":824,"passed_time":3.170706589,"remaining_time":0.672574125},
{"learn":[4.856787127],"iteration":825,"passed_time":3.174238631,"remaining_time":0.6686652806},
{"learn":[4.821955405],"iteration":826,"passed_time":3.177570066,"remaining_time":0.6647153825},
{"learn":[4.792480486],"iteration":827,"passed_time":3.179589667,"remaining_time":0.6604944719},
{"learn":[4.783448444],"iteration":828,"passed_time":3.182871126,"remaining_time":0.6565391588},
{"learn":[4.745042394],"iteration":829,"passed_time":3.186015208,"remaining_time":0.6525573317},
{"learn":[4.711869089],"iteration":830,"passed_time":3.187998802,"remaining_time":0.6483415134},
{"learn":[4.703783505],"iteration":831,"passed_time":3.189705269,"remaining_time":0.6440751023},
{"learn":[4.673415862],"iteration":832,"passed_time":3.191406088,"remaining_time":0.6398137056},
{"learn":[4.643444785],"iteration":833,"passed_time":3.19310703,"remaining_time":0.6355584736},
{"learn":[4.624096004],"iteration":834,"passed_time":3.195323228,"remaining_time":0.6314111769},
{"learn":[4.602547561],"iteration":835,"passed_time":3.198613917,"remaining_time":0.6274792851},
{"learn":[4.594409354],"iteration":836,"passed_time":3.201394321,"remaining_time":0.6234495511},
{"learn":[4.56721743],"iteration":837,"passed_time":3.203126727,"remaining_time":0.6192202025},
{"learn":[4.537908651],"iteration":838,"passed_time":3.206494287,"remaining_time":0.6153105843},
{"learn":[4.506281186],"iteration":839,"passed_time":3.211416768,"remaining_time":0.611698432},
{"learn":[4.47975738],"iteration":840,"passed_time":3.214096498,"remaining_time":0.6076591476},
{"learn":[4.442624799],"iteration":841,"passed_time":3.21677008,"remaining_time":0.603621939},
{"learn":[4.414225548],"iteration":842,"passed_time":3.220241761,"remaining_time":0.5997366033},
{"learn":[4.378923938],"iteration":843,"passed_time":3.223794385,"remaining_time":0.5958672086},
{"learn":[4.343215379],"iteration":844,"passed_time":3.227296846,"remaining_time":0.5919893622},
{"learn":[4.333741519],"iteration":845,"passed_time":3.230991313,"remaining_time":0.5881473548},
{"learn":[4.306137039],"iteration":846,"passed_time":3.234375537,"remaining_time":0.5842496542},
{"learn":[4.280806623],"iteration":847,"passed_time":3.2362752,"remaining_time":0.5800870642},
{"learn":[4.251126797],"iteration":848,"passed_time":3.238142169,"remaining_time":0.5759239899},
{"learn":[4.241897171],"iteration":849,"passed_time":3.241573548,"remaining_time":0.5720423908},
{"learn":[4.214969032],"iteration":850,"passed_time":3.245628276,"remaining_time":0.5682709907},
{"learn":[4.185950985],"iteration":851,"passed_time":3.249209808,"remaining_time":0.5644167273},
{"learn":[4.176891497],"iteration":852,"passed_time":3.252628792,"remaining_time":0.5605350908},
{"learn":[4.14325995],"iteration":853,"passed_time":3.256025248,"remaining_time":0.5566506865},
{"learn":[4.134375355],"iteration":854,"passed_time":3.259570927,"remaining_time":0.5527927302},
{"learn":[4.108538626],"iteration":855,"passed_time":3.263612815,"remaining_time":0.5490189783},
{"learn":[4.087388481],"iteration":856,"passed_time":3.267040536,"remaining_time":0.5451421198},
{"learn":[4.058788293],"iteration":857,"passed_time":3.26948689,"remaining_time":0.5411038909},
{"learn":[4.02863072],"iteration":858,"passed_time":3.272882708,"remaining_time":0.5372252174},
{"learn":[3.998917469],"iteration":859,"passed_time":3.276336822,"remaining_time":0.5333571571},
{"learn":[3.975244183],"iteration":860,"passed_time":3.27823307,"remaining_time":0.529238556},
{"learn":[3.948018973],"iteration":861,"passed_time":3.281625597,"remaining_time":0.5253646548},
{"learn":[3.94127451],"iteration":862,"passed_time":3.284957398,"remaining_time":0.5214822289},
{"learn":[3.914390042],"iteration":863,"passed_time":3.288274262,"remaining_time":0.5175987264},
{"learn":[3.90772601],"iteration":864,"passed_time":3.291771703,"remaining_time":0.5137447166},
{"learn":[3.8766704],"iteration":865,"passed_time":3.295050275,"remaining_time":0.5098576639},
{"learn":[3.861436165],"iteration":866,"passed_time":3.29776729,"remaining_time":0.5058858703},
{"learn":[3.836930263],"iteration":867,"passed_time":3.299729829,"remaining_time":0.501802232},
{"learn":[3.8087303],"iteration":868,"passed_time":3.301882839,"remaining_time":0.4977521887},
{"learn":[3.78628895],"iteration":869,"passed_time":3.304560804,"remaining_time":0.4937849478},
{"learn":[3.760552191],"iteration":870,"passed_time":3.307578704,"remaining_time":0.4898710136},
{"learn":[3.745833399],"iteration":871,"passed_time":3.312304586,"remaining_time":0.4862098476},
{"learn":[3.720437969],"iteration":872,"passed_time":3.314040692,"remaining_time":0.4821113034},
{"learn":[3.701458603],"iteration":873,"passed_time":3.315758835,"remaining_time":0.4780155757},
{"learn":[3.674413311],"iteration":874,"passed_time":3.317477929,"remaining_time":0.4739254184},
{"learn":[3.660082272],"iteration":875,"passed_time":3.32281819,"remaining_time":0.4703532597},
{"learn":[3.652066313],"iteration":876,"passed_time":3.324617754,"remaining_time":0.4662804832},
{"learn":[3.627310034],"iteration":877,"passed_time":3.327078808,"remaining_time":0.4623048003},
{"learn":[3.606172306],"iteration":878,"passed_time":3.33043108,"remaining_time":0.4584552453},
{"learn":[3.581797358],"iteration":879,"passed_time":3.334633317,"remaining_time":0.4547227251},
{"learn":[3.557587679],"iteration":880,"passed_time":3.336788079,"remaining_time":0.4507125782},
{"learn":[3.543736712],"iteration":881,"passed_time":3.340238916,"remaining_time":0.4468800363},
{"learn":[3.535978552],"iteration":882,"passed_time":3.34222127,"remaining_time":0.442853781},
{"learn":[3.510258441],"iteration":883,"passed_time":3.344115198,"remaining_time":0.4388205464},
{"learn":[3.502642042],"iteration":884,"passed_time":3.346114918,"remaining_time":0.4348058933},
{"learn":[3.479048208],"iteration":885,"passed_time":3.353472423,"remaining_time":0.431485165},
{"learn":[3.471931665],"iteration":886,"passed_time":3.357150691,"remaining_time":0.4276866156},
{"learn":[3.448639247],"iteration":887,"passed_time":3.360465267,"remaining_time":0.4238424662},
{"learn":[3.441628343],"iteration":888,"passed_time":3.364671858,"remaining_time":0.4201108844},
{"learn":[3.435346285],"iteration":889,"passed_time":3.368533623,"remaining_time":0.4163356163},
{"learn":[3.41235563],"iteration":890,"passed_time":3.37186695,"remaining_time":0.4124955079},
{"learn":[3.405506552],"iteration":891,"passed_time":3.375189105,"remaining_time":0.4086551831},
{"learn":[3.382047956],"iteration":892,"passed_time":3.377517872,"remaining_time":0.4046969903},
{"learn":[3.359523862],"iteration":893,"passed_time":3.382044119,"remaining_time":0.401002994},
{"learn":[3.352817457],"iteration":894,"passed_time":3.385496832,"remaining_time":0.3971811926},
{"learn":[3.33380007],"iteration":895,"passed_time":3.388967893,"remaining_time":0.3933623447},
{"learn":[3.311525914],"iteration":896,"passed_time":3.392620272,"remaining_time":0.3895650926},
{"learn":[3.304976911],"iteration":897,"passed_time":3.395224393,"remaining_time":0.3856490958},
{"learn":[3.282980816],"iteration":898,"passed_time":3.398185804,"remaining_time":0.3817761582},
{"learn":[3.276527326],"iteration":899,"passed_time":3.401360526,"remaining_time":0.3779289473},
{"learn":[3.270161597],"iteration":900,"passed_time":3.40303868,"remaining_time":0.3739187895},
{"learn":[3.248451064],"iteration":901,"passed_time":3.405217173,"remaining_time":0.3699681629},
{"learn":[3.226872758],"iteration":902,"passed_time":3.407796738,"remaining_time":0.3660645444},
{"learn":[3.220637948],"iteration":903,"passed_time":3.40951657,"remaining_time":0.3620725561},
{"learn":[3.200864578],"iteration":904,"passed_time":3.411500361,"remaining_time":0.3581132976},
{"learn":[3.195136921],"iteration":905,"passed_time":3.413911055,"remaining_time":0.3542026922},
{"learn":[3.174032238],"iteration":906,"passed_time":3.415630584,"remaining_time":0.3502245252},
{"learn":[3.167950566],"iteration":907,"passed_time":3.417293027,"remaining_time":0.346245549},
{"learn":[3.148609362],"iteration":908,"passed_time":3.41972587,"remaining_time":0.3423487945},
{"learn":[3.143010419],"iteration":909,"passed_time":3.422451776,"remaining_time":0.3384842416},
{"learn":[3.122354321],"iteration":910,"passed_time":3.426204078,"remaining_time":0.334722462},
{"learn":[3.116819379],"iteration":911,"passed_time":3.429674994,"remaining_time":0.330933552},
{"learn":[3.095552207],"iteration":912,"passed_time":3.433164638,"remaining_time":0.3271471232},
{"learn":[3.082944626],"iteration":913,"passed_time":3.436803533,"remaining_time":0.3233753871},
{"learn":[3.061891137],"iteration":914,"passed_time":3.440269356,"remaining_time":0.3195878637},
{"learn":[3.043323435],"iteration":915,"passed_time":3.443813163,"remaining_time":0.315808194},
{"learn":[3.023473283],"iteration":916,"passed_time":3.447165517,"remaining_time":0.3120117098},
{"learn":[3.018103198],"iteration":917,"passed_time":3.450673139,"remaining_time":0.3082300626},
{"learn":[3.003856452],"iteration":918,"passed_time":3.453907833,"remaining_time":0.3044249559},
{"learn":[2.988149693],"iteration":919,"passed_time":3.457216318,"remaining_time":0.3006275059},
{"learn":[2.967812077],"iteration":920,"passed_time":3.46048479,"remaining_time":0.2968276856},
{"learn":[2.950985179],"iteration":921,"passed_time":3.463904116,"remaining_time":0.2930417799},
{"learn":[2.934328441],"iteration":922,"passed_time":3.467189686,"remaining_time":0.2892455101},
{"learn":[2.917840074],"iteration":923,"passed_time":3.470446758,"remaining_time":0.2854480017},
{"learn":[2.901518311],"iteration":924,"passed_time":3.473406995,"remaining_time":0.2816275942},
{"learn":[2.88536141],"iteration":925,"passed_time":3.47671413,"remaining_time":0.2778367664},
{"learn":[2.880154061],"iteration":926,"passed_time":3.480271983,"remaining_time":0.2740667258},
{"learn":[2.864171011],"iteration":927,"passed_time":3.481938783,"remaining_time":0.2701504228},
{"learn":[2.848349203],"iteration":928,"passed_time":3.483595096,"remaining_time":0.2662381613},
{"learn":[2.842846283],"iteration":929,"passed_time":3.487075589,"remaining_time":0.2624680551},
{"learn":[2.827199593],"iteration":930,"passed_time":3.488954432,"remaining_time":0.2585798666},
{"learn":[2.811710446],"iteration":931,"passed_time":3.490666993,"remaining_time":0.2546838579},
{"learn":[2.79637721],"iteration":932,"passed_time":3.494120314,"remaining_time":0.2509175359},
{"learn":[2.774172322],"iteration":933,"passed_time":3.497278581,"remaining_time":0.2471310346},
{"learn":[2.769137391],"iteration":934,"passed_time":3.500514913,"remaining_time":0.2433513041},
{"learn":[2.748144638],"iteration":935,"passed_time":3.503798571,"remaining_time":0.2395759706},
{"learn":[2.743202626],"iteration":936,"passed_time":3.507214346,"remaining_time":0.2358105697},
{"learn":[2.728300341],"iteration":937,"passed_time":3.510339906,"remaining_time":0.2320267315},
{"learn":[2.707726623],"iteration":938,"passed_time":3.512136795,"remaining_time":0.2281579813},
{"learn":[2.693092836],"iteration":939,"passed_time":3.514060356,"remaining_time":0.2243017248},
{"learn":[2.672901385],"iteration":940,"passed_time":3.517156802,"remaining_time":0.2205231151},
{"learn":[2.668090195],"iteration":941,"passed_time":3.520383056,"remaining_time":0.2167539461},
{"learn":[2.650221392],"iteration":942,"passed_time":3.523978204,"remaining_time":0.2130082266},
{"learn":[2.645475008],"iteration":943,"passed_time":3.525605331,"remaining_time":0.2091460789},
{"learn":[2.625729854],"iteration":944,"passed_time":3.527216678,"remaining_time":0.2052877432},
{"learn":[2.606090751],"iteration":945,"passed_time":3.528809598,"remaining_time":0.201433106},
{"learn":[2.588731858],"iteration":946,"passed_time":3.530718239,"remaining_time":0.1976009152},
{"learn":[2.584100038],"iteration":947,"passed_time":3.532304701,"remaining_time":0.1937551102},
{"learn":[2.579526601],"iteration":948,"passed_time":3.535065201,"remaining_time":0.1899771605},
{"learn":[2.565659911],"iteration":949,"passed_time":3.537695369,"remaining_time":0.1861944931},
{"learn":[2.54866299],"iteration":950,"passed_time":3.539716897,"remaining_time":0.1823828896},
{"learn":[2.544153679],"iteration":951,"passed_time":3.541661262,"remaining_time":0.178571156},
{"learn":[2.527136296],"iteration":952,"passed_time":3.543638354,"remaining_time":0.1747649555},
{"learn":[2.510298338],"iteration":953,"passed_time":3.545392547,"remaining_time":0.1709518419},
{"learn":[2.505879551],"iteration":954,"passed_time":3.547106001,"remaining_time":0.1671411204},
{"learn":[2.489240533],"iteration":955,"passed_time":3.549358241,"remaining_time":0.1633595843},
{"learn":[2.472776779],"iteration":956,"passed_time":3.552552328,"remaining_time":0.1596235633},
{"learn":[2.458193237],"iteration":957,"passed_time":3.555759987,"remaining_time":0.1558892687},
{"learn":[2.443977326],"iteration":958,"passed_time":3.558869649,"remaining_time":0.1521518828},
{"learn":[2.431031533],"iteration":959,"passed_time":3.560643051,"remaining_time":0.1483601271},
{"learn":[2.41712807],"iteration":960,"passed_time":3.562232518,"remaining_time":0.1445651074},
{"learn":[2.404257488],"iteration":961,"passed_time":3.564261889,"remaining_time":0.1407920497},
{"learn":[2.391404901],"iteration":962,"passed_time":3.567918464,"remaining_time":0.1370851331},
{"learn":[2.378772023],"iteration":963,"passed_time":3.570465946,"remaining_time":0.1333369025},
{"learn":[2.360242243],"iteration":964,"passed_time":3.572113495,"remaining_time":0.1295585205},
{"learn":[2.341973555],"iteration":965,"passed_time":3.574927712,"remaining_time":0.1258256131},
{"learn":[2.32964013],"iteration":966,"passed_time":3.578474853,"remaining_time":0.1221196175},
{"learn":[2.317455973],"iteration":967,"passed_time":3.582325622,"remaining_time":0.1184239875},
{"learn":[2.304384051],"iteration":968,"passed_time":3.584095206,"remaining_time":0.1146614565},
{"learn":[2.292302694],"iteration":969,"passed_time":3.586295577,"remaining_time":0.1109163581},
{"learn":[2.2750851],"iteration":970,"passed_time":3.589548587,"remaining_time":0.1072058795},
{"learn":[2.263282291],"iteration":971,"passed_time":3.59291879,"remaining_time":0.1034997182},
{"learn":[2.251488719],"iteration":972,"passed_time":3.596417783,"remaining_time":0.0997978213},
{"learn":[2.241051242],"iteration":973,"passed_time":3.599806475,"remaining_time":0.09609339666},
{"learn":[2.223736852],"iteration":974,"passed_time":3.603188649,"remaining_time":0.09238945254},
{"learn":[2.211318813],"iteration":975,"passed_time":3.606619375,"remaining_time":0.08868736169},
{"learn":[2.194321752],"iteration":976,"passed_time":3.610417293,"remaining_time":0.08499447056},
{"learn":[2.182949205],"iteration":977,"passed_time":3.614497909,"remaining_time":0.08130772393},
{"learn":[2.172875286],"iteration":978,"passed_time":3.617886951,"remaining_time":0.07760533808},
{"learn":[2.156201239],"iteration":979,"passed_time":3.621398594,"remaining_time":0.07390609376},
{"learn":[2.145070556],"iteration":980,"passed_time":3.624964905,"remaining_time":0.07020829072},
{"learn":[2.134074366],"iteration":981,"passed_time":3.628407575,"remaining_time":0.06650848916},
{"learn":[2.124293577],"iteration":982,"passed_time":3.630706068,"remaining_time":0.06278942336},
{"learn":[2.11462434],"iteration":983,"passed_time":3.633984345,"remaining_time":0.05908917635},
{"learn":[2.103704597],"iteration":984,"passed_time":3.636098257,"remaining_time":0.05537205468},
{"learn":[2.094189541],"iteration":985,"passed_time":3.638116497,"remaining_time":0.05165682653},
{"learn":[2.084783124],"iteration":986,"passed_time":3.639764345,"remaining_time":0.04794015854},
{"learn":[2.068815121],"iteration":987,"passed_time":3.641545668,"remaining_time":0.04422929962},
{"learn":[2.053059518],"iteration":988,"passed_time":3.644885053,"remaining_time":0.04053967198},
{"learn":[2.037513768],"iteration":989,"passed_time":3.646685685,"remaining_time":0.03683520894},
{"learn":[2.025376894],"iteration":990,"passed_time":3.648315184,"remaining_time":0.03313303396},
{"learn":[2.014936698],"iteration":991,"passed_time":3.649924421,"remaining_time":0.02943487436},
{"learn":[2.002967612],"iteration":992,"passed_time":3.651555594,"remaining_time":0.0257410767},
{"learn":[1.988068254],"iteration":993,"passed_time":3.654233484,"remaining_time":0.02205774739},
{"learn":[1.973336407],"iteration":994,"passed_time":3.657406754,"remaining_time":0.01837892841},
{"learn":[1.961634971],"iteration":995,"passed_time":3.6606171,"remaining_time":0.01470127349},
{"learn":[1.947138072],"iteration":996,"passed_time":3.663591948,"remaining_time":0.01102384739},
{"learn":[1.932804204],"iteration":997,"passed_time":3.666883516,"remaining_time":0.00734846396},
{"learn":[1.921363598],"iteration":998,"passed_time":3.670133879,"remaining_time":0.003673807687},
{"learn":[1.911498123],"iteration":999,"passed_time":3.673392994,"remaining_time":0}
]}